{
"metadata": {
    "version": {
        "essentia": "2.1-beta2"
    }
},
"values": {
    "barkbands_kurtosis": {
        "ARc0p1": [0.296358466148],
        "ARc0p2": [59.0684547424],
        "ARc1p1": [-1.17549435082e-38],
        "ARc1p2": [0.0178659558296],
        "ARc2p1": [0.557900309563],
        "ARc2p2": [0.0166224520653],
        "ARc3p1": [-1.17549435082e-38],
        "ARc3p2": [-1.17549435082e-38],
        "ARc4p1": [1.76660382748],
        "ARc4p2": [0.2832262218],
        "ARerrp1": [0.142761588097],
        "ARerrp2": [83.6707305908],
        "Accelerationp1": [101.979354858],
        "Accelerationp2": [10535.6542969],
        "Centroidp1": [0.233069807291],
        "Centroidp2": [0.866155564785],
        "Derivativep1": [278.288360596],
        "Derivativep2": [11776.8193359],
        "Meanp1": [8.02299118042],
        "Meanp2": [82.1118240356],
        "Medianp1": [3.27877187729],
        "Medianp2": [16.0853176117],
        "SpKurtp1": [0.0575215816498],
        "SpKurtp2": [-1.0785779953],
        "SpSkewp1": [1.11534237862],
        "SpSkewp2": [0.210313409567],
        "SpSpreadp1": [0.0893320068717],
        "SpSpreadp2": [0.0832946076989],
        "pointdiffp1": [-26.2719707489],
        "pointdiffp2": [628.735595703],
        "pointmiddlep1": [0.944853067398],
        "pointmiddlep2": [0.0951385945082],
        "pointstartp1": [28.4634590149],
        "pointstartp2": [-62.6452064514],
        "slopeendp1": [-1.83475089073],
        "slopeendp2": [156.255889893],
        "slopeerrorp1": [0.0363983176649],
        "slopeerrorp2": [0.178285717964],
        "slopemiddlep1": [-62.1203575134],
        "slopemiddlep2": [-7.85229873657],
        "slopestartp1": [-148.744476318],
        "slopestartp2": [113.243400574],
        "stddevp1": [6.91796207428],
        "stddevp2": [101.02734375]
    },
    "barkbands_skewness": {
        "ARc0p1": [-1.17549435082e-38],
        "ARc0p2": [0.85466170311],
        "ARc1p1": [-1.17549435082e-38],
        "ARc1p2": [0.161482617259],
        "ARc2p1": [0.951896548271],
        "ARc2p2": [0.0695405602455],
        "ARc3p1": [-1.17549435082e-38],
        "ARc3p2": [0.00852881930768],
        "ARc4p1": [1.95884490013],
        "ARc4p2": [0.576606154442],
        "ARerrp1": [0.0266267694533],
        "ARerrp2": [1.07083177567],
        "Accelerationp1": [12.8423032761],
        "Accelerationp2": [88.4219894409],
        "Centroidp1": [0.385185688734],
        "Centroidp2": [0.729188621044],
        "Derivativep1": [35.9104270935],
        "Derivativep2": [111.648521423],
        "Meanp1": [-2.46258687973],
        "Meanp2": [4.63819122314],
        "Medianp1": [-1.91467642784],
        "Medianp2": [3.76894712448],
        "SpKurtp1": [0.23399066925],
        "SpKurtp2": [-0.912806272507],
        "SpSkewp1": [1.25065422058],
        "SpSkewp2": [0.488494455814],
        "SpSpreadp1": [0.0949254333973],
        "SpSpreadp2": [0.0886345878243],
        "pointdiffp1": [3.26971197128],
        "pointdiffp2": [7.46985387802],
        "pointmiddlep1": [0.877390801907],
        "pointmiddlep2": [0.647113025188],
        "pointstartp1": [-4.8686671257],
        "pointstartp2": [0.171041712165],
        "slopeendp1": [-4.17066860199],
        "slopeendp2": [-144.49546814],
        "slopeerrorp1": [0.0368990525603],
        "slopeerrorp2": [0.187676101923],
        "slopemiddlep1": [74.7183151245],
        "slopemiddlep2": [140.267700195],
        "slopestartp1": [142.931564331],
        "slopestartp2": [-125.620285034],
        "stddevp1": [0.887333035469],
        "stddevp2": [3.919495821]
    },
    "barkbands_spread": {
        "ARc0p1": [4.98985052109],
        "ARc0p2": [0.20111733675],
        "ARc1p1": [-1.17549435082e-38],
        "ARc1p2": [0.07280382514],
        "ARc2p1": [0.979669451714],
        "ARc2p2": [0.131543308496],
        "ARc3p1": [-1.17549435082e-38],
        "ARc3p2": [-1.17549435082e-38],
        "ARc4p1": [1.86923992634],
        "ARc4p2": [1.29994142056],
        "ARerrp1": [0.601463794708],
        "ARerrp2": [0.942208588123],
        "Accelerationp1": [214.625411987],
        "Accelerationp2": [141.045639038],
        "Centroidp1": [0.606157302856],
        "Centroidp2": [0.338355511427],
        "Derivativep1": [323.511322021],
        "Derivativep2": [186.979644775],
        "Meanp1": [21.7208518982],
        "Meanp2": [17.7706794739],
        "Medianp1": [26.6063613892],
        "Medianp2": [10.4332056046],
        "SpKurtp1": [1.44717645645],
        "SpKurtp2": [2.57908439636],
        "SpSkewp1": [1.62879109383],
        "SpSkewp2": [1.79954707623],
        "SpSpreadp1": [0.079669162631],
        "SpSpreadp2": [0.050912398845],
        "pointdiffp1": [24.5077323914],
        "pointdiffp2": [-5.70120859146],
        "pointmiddlep1": [0.88555675745],
        "pointmiddlep2": [3.9967250824],
        "pointstartp1": [3.56128501892],
        "pointstartp2": [33.9046325684],
        "slopeendp1": [-58.8508987427],
        "slopeendp2": [177.003646851],
        "slopeerrorp1": [0.0918999090791],
        "slopeerrorp2": [0.719280421734],
        "slopemiddlep1": [90.6222457886],
        "slopemiddlep2": [-171.60194397],
        "slopestartp1": [136.717926025],
        "slopestartp2": [168.858444214],
        "stddevp1": [7.85355758667],
        "stddevp2": [12.9703121185]
    },
    "envelope": {
        "ARc0p1": [3.01397631119e-06],
        "ARc0p2": [-1.17549435082e-38],
        "ARc1p1": [-1.17549435082e-38],
        "ARc1p2": [-1.17549435082e-38],
        "ARc2p1": [0.220308035612],
        "ARc2p2": [0.167019873857],
        "ARc3p1": [-1.17549435082e-38],
        "ARc3p2": [-1.17549435082e-38],
        "ARc4p1": [1.29777193069],
        "ARc4p2": [1.37226641178],
        "ARerrp1": [3.23815584125e-06],
        "ARerrp2": [2.98723978887e-09],
        "Accelerationp1": [0.148172542453],
        "Accelerationp2": [8.29295968288e-05],
        "Centroidp1": [0.596659719944],
        "Centroidp2": [0.159396857023],
        "Derivativep1": [0.12054438889],
        "Derivativep2": [0.00106485595461],
        "Meanp1": [0.00889821723104],
        "Meanp2": [0.00185898016207],
        "Medianp1": [0.0104683944955],
        "Medianp2": [0.000484391493956],
        "SpKurtp1": [7.53324222565],
        "SpKurtp2": [7.72292804718],
        "SpSkewp1": [2.83695244789],
        "SpSkewp2": [2.86701989174],
        "SpSpreadp1": [0.038456402719],
        "SpSpreadp2": [0.0379339419305],
        "pointdiffp1": [0.0140167353675],
        "pointdiffp2": [-0.0113426363096],
        "pointmiddlep1": [0.919396996498],
        "pointmiddlep2": [0.934814929962],
        "pointstartp1": [-0.00202829879709],
        "pointstartp2": [0.0108182132244],
        "slopeendp1": [65.5034713745],
        "slopeendp2": [-84.6859283447],
        "slopeerrorp1": [0.0289648082107],
        "slopeerrorp2": [0.0186219550669],
        "slopemiddlep1": [37.5126152039],
        "slopemiddlep2": [-19.8216762543],
        "slopestartp1": [151.91758728],
        "slopestartp2": [-154.334640503],
        "stddevp1": [0.00270148552954],
        "stddevp2": [0.00204747635871]
    },
    "mfcc0": {
        "ARc0p1": [261.505401611],
        "ARc0p2": [-1.17549435082e-38],
        "ARc1p1": [-1.17549435082e-38],
        "ARc1p2": [-1.17549435082e-38],
        "ARc2p1": [0.760187268257],
        "ARc2p2": [0.603753507137],
        "ARc3p1": [-1.17549435082e-38],
        "ARc3p2": [-1.17549435082e-38],
        "ARc4p1": [1.52971172333],
        "ARc4p2": [1.41617321968],
        "ARerrp1": [1.22213077545],
        "ARerrp2": [0.375278502703],
        "Accelerationp1": [1230.89306641],
        "Accelerationp2": [60.1082382202],
        "Centroidp1": [0.494769454002],
        "Centroidp2": [0.503985762596],
        "Derivativep1": [2201.5144043],
        "Derivativep2": [76.4565811157],
        "Meanp1": [-990.433105469],
        "Meanp2": [-1128.29138184],
        "Medianp1": [-976.030212402],
        "Medianp2": [-1138.42004395],
        "SpKurtp1": [0.162966966629],
        "SpKurtp2": [41.6849708557],
        "SpSkewp1": [1.2933216095],
        "SpSkewp2": [6.22812509537],
        "SpSpreadp1": [0.104244254529],
        "SpSpreadp2": [0.0109919989482],
        "pointdiffp1": [115.998977661],
        "pointdiffp2": [-119.852432251],
        "pointmiddlep1": [1.19091272354],
        "pointmiddlep2": [0.938246369362],
        "pointstartp1": [-1098.5234375],
        "pointstartp2": [-1033.38366699],
        "slopeendp1": [109.994438171],
        "slopeendp2": [-127.021812439],
        "slopeerrorp1": [0.0952161774039],
        "slopeerrorp2": [0.060782186687],
        "slopemiddlep1": [-61.5748634338],
        "slopemiddlep2": [41.5941543579],
        "slopestartp1": [163.63734436],
        "slopestartp2": [-159.437026978],
        "stddevp1": [23.3586921692],
        "stddevp2": [16.3645420074]
    },
    "mfcc1": {
        "ARc0p1": [-1.17549435082e-38],
        "ARc0p2": [0.0494026504457],
        "ARc1p1": [-1.17549435082e-38],
        "ARc1p2": [0.00966163259],
        "ARc2p1": [0.0923846587539],
        "ARc2p2": [0.405408024788],
        "ARc3p1": [-1.17549435082e-38],
        "ARc3p2": [-1.17549435082e-38],
        "ARc4p1": [0.772860229015],
        "ARc4p2": [1.31979751587],
        "ARerrp1": [1.02427017689],
        "ARerrp2": [0.385285764933],
        "Accelerationp1": [334.30670166],
        "Accelerationp2": [59.7703094482],
        "Centroidp1": [0.513410210609],
        "Centroidp2": [0.136438325047],
        "Derivativep1": [620.9921875],
        "Derivativep2": [66.1812438965],
        "Meanp1": [-21.896112442],
        "Meanp2": [1.21794807911],
        "Medianp1": [-22.3111686707],
        "Medianp2": [1.14440917969e-05],
        "SpKurtp1": [2.92827367783],
        "SpKurtp2": [1.27013063431],
        "SpSkewp1": [1.89272320271],
        "SpSkewp2": [1.39042782784],
        "SpSpreadp1": [0.0610473230481],
        "SpSpreadp2": [0.0548478737473],
        "pointdiffp1": [-12.1903266907],
        "pointdiffp2": [-3.20062637329],
        "pointmiddlep1": [1.3443145752],
        "pointmiddlep2": [1.34291696548],
        "pointstartp1": [-9.36815452576],
        "pointstartp2": [4.61589384079],
        "slopeendp1": [-130.15171814],
        "slopeendp2": [159.992630005],
        "slopeerrorp1": [0.230611488223],
        "slopeerrorp2": [0.576095402241],
        "slopemiddlep1": [103.328437805],
        "slopemiddlep2": [-138.632385254],
        "slopestartp1": [-167.188171387],
        "slopestartp2": [-94.1071090698],
        "stddevp1": [3.96359753609],
        "stddevp2": [2.4392285347]
    },
    "mfcc10": {
        "ARc0p1": [1.84925937653],
        "ARc0p2": [-1.17549435082e-38],
        "ARc1p1": [-1.17549435082e-38],
        "ARc1p2": [-1.17549435082e-38],
        "ARc2p1": [-1.17549435082e-38],
        "ARc2p2": [0.426197379827],
        "ARc3p1": [-1.17549435082e-38],
        "ARc3p2": [-1.17549435082e-38],
        "ARc4p1": [1.04570877552],
        "ARc4p2": [1.38072037697],
        "ARerrp1": [0.830317795277],
        "ARerrp2": [0.376739382744],
        "Accelerationp1": [308.166137695],
        "Accelerationp2": [57.0331306458],
        "Centroidp1": [0.717024147511],
        "Centroidp2": [0.16017191112],
        "Derivativep1": [328.261871338],
        "Derivativep2": [68.2056427002],
        "Meanp1": [4.52784013748],
        "Meanp2": [-0.415852606297],
        "Medianp1": [5.79706192017],
        "Medianp2": [-2.67028808594e-05],
        "SpKurtp1": [1.63676738739],
        "SpKurtp2": [0.740861177444],
        "SpSkewp1": [1.67636632919],
        "SpSkewp2": [1.1328163147],
        "SpSpreadp1": [0.0764401555061],
        "SpSpreadp2": [0.0493390895426],
        "pointdiffp1": [5.24697637558],
        "pointdiffp2": [0.270558714867],
        "pointmiddlep1": [2.00305008888],
        "pointmiddlep2": [2.70914411545],
        "pointstartp1": [-3.02469158173],
        "pointstartp2": [-0.949409365654],
        "slopeendp1": [-169.698532104],
        "slopeendp2": [-176.649734497],
        "slopeerrorp1": [0.18763063848],
        "slopeerrorp2": [3.43854093552],
        "slopemiddlep1": [152.198181152],
        "slopemiddlep2": [171.930023193],
        "slopestartp1": [85.9264144897],
        "slopestartp2": [-173.069900513],
        "stddevp1": [3.87307834625],
        "stddevp2": [1.02172207832]
    },
    "mfcc11": {
        "ARc0p1": [-1.17549435082e-38],
        "ARc0p2": [-1.17549435082e-38],
        "ARc1p1": [-1.17549435082e-38],
        "ARc1p2": [-1.17549435082e-38],
        "ARc2p1": [0.430949389935],
        "ARc2p2": [0.632251560688],
        "ARc3p1": [-1.17549435082e-38],
        "ARc3p2": [-1.17549435082e-38],
        "ARc4p1": [1.40581119061],
        "ARc4p2": [1.47537076473],
        "ARerrp1": [1.38574159145],
        "ARerrp2": [0.338840842247],
        "Accelerationp1": [324.780731201],
        "Accelerationp2": [50.2133560181],
        "Centroidp1": [3.35924100876],
        "Centroidp2": [0.11302036792],
        "Derivativep1": [509.67489624],
        "Derivativep2": [66.9954223633],
        "Meanp1": [-0.46496963501],
        "Meanp2": [-0.712531745434],
        "Medianp1": [-1.32177734375],
        "Medianp2": [-3.0517578125e-05],
        "SpKurtp1": [0.770839691162],
        "SpKurtp2": [0.849282979965],
        "SpSkewp1": [1.07060945034],
        "SpSkewp2": [1.18434154987],
        "SpSpreadp1": [0.0339161008596],
        "SpSpreadp2": [0.0490540936589],
        "pointdiffp1": [-15.8931541443],
        "pointdiffp2": [3.86309289932],
        "pointmiddlep1": [0.567208647728],
        "pointmiddlep2": [1.07091879845],
        "pointstartp1": [8.14920520782],
        "pointstartp2": [-4.11366462708],
        "slopeendp1": [-108.451377869],
        "slopeendp2": [-58.5674285889],
        "slopeerrorp1": [0.203939825296],
        "slopeerrorp2": [0.254176557064],
        "slopemiddlep1": [-67.7760772705],
        "slopemiddlep2": [65.1217193604],
        "slopestartp1": [-125.11076355],
        "slopestartp2": [151.972229004],
        "stddevp1": [4.89743089676],
        "stddevp2": [1.38892781734]
    },
    "mfcc12": {
        "ARc0p1": [1.41886436939],
        "ARc0p2": [0.0336318537593],
        "ARc1p1": [-1.17549435082e-38],
        "ARc1p2": [-1.17549435082e-38],
        "ARc2p1": [0.741198718548],
        "ARc2p2": [0.506946980953],
        "ARc3p1": [-1.17549435082e-38],
        "ARc3p2": [-1.17549435082e-38],
        "ARc4p1": [1.57267999649],
        "ARc4p2": [1.35502457619],
        "ARerrp1": [0.497063696384],
        "ARerrp2": [0.302650749683],
        "Accelerationp1": [215.713516235],
        "Accelerationp2": [48.0071601868],
        "Centroidp1": [0.890086472034],
        "Centroidp2": [0.10554998368],
        "Derivativep1": [257.881591797],
        "Derivativep2": [61.0574645996],
        "Meanp1": [3.26334285736],
        "Meanp2": [0.297981590033],
        "Medianp1": [5.46160125732],
        "Medianp2": [-3.81469726562e-05],
        "SpKurtp1": [2.13907527924],
        "SpKurtp2": [0.342235565186],
        "SpSkewp1": [1.69215524197],
        "SpSkewp2": [0.987175703049],
        "SpSpreadp1": [0.0652530565858],
        "SpSpreadp2": [0.0540066622198],
        "pointdiffp1": [10.0935945511],
        "pointdiffp2": [-1.74456095695],
        "pointmiddlep1": [0.814511120319],
        "pointmiddlep2": [1.06491744518],
        "pointstartp1": [-3.76754689217],
        "pointstartp2": [1.82695364952],
        "slopeendp1": [-134.116409302],
        "slopeendp2": [33.0438232422],
        "slopeerrorp1": [0.14427909255],
        "slopeerrorp2": [0.397979468107],
        "slopemiddlep1": [128.042739868],
        "slopemiddlep2": [-54.8117904663],
        "slopestartp1": [17.4647064209],
        "slopestartp2": [-153.354537964],
        "stddevp1": [4.4035282135],
        "stddevp2": [0.863707184792]
    },
    "mfcc2": {
        "ARc0p1": [-1.17549435082e-38],
        "ARc0p2": [-1.17549435082e-38],
        "ARc1p1": [0.0592023096979],
        "ARc1p2": [0.0466896221042],
        "ARc2p1": [0.0355000421405],
        "ARc2p2": [0.443340331316],
        "ARc3p1": [-1.17549435082e-38],
        "ARc3p2": [-1.17549435082e-38],
        "ARc4p1": [0.917271912098],
        "ARc4p2": [1.46876943111],
        "ARerrp1": [0.748210430145],
        "ARerrp2": [0.356989383698],
        "Accelerationp1": [481.010528564],
        "Accelerationp2": [60.4397392273],
        "Centroidp1": [0.5227470994],
        "Centroidp2": [0.0476042106748],
        "Derivativep1": [487.653289795],
        "Derivativep2": [72.0490875244],
        "Meanp1": [-29.710647583],
        "Meanp2": [-3.98620796204],
        "Medianp1": [-30.870803833],
        "Medianp2": [-6.103515625e-05],
        "SpKurtp1": [0.954940080643],
        "SpKurtp2": [2.51166296005],
        "SpSkewp1": [1.44740402699],
        "SpSkewp2": [1.78440904617],
        "SpSpreadp1": [0.0729975551367],
        "SpSpreadp2": [0.0515466704965],
        "pointdiffp1": [-14.8237409592],
        "pointdiffp2": [49.7502937317],
        "pointmiddlep1": [0.750726282597],
        "pointmiddlep2": [0.937730491161],
        "pointstartp1": [-19.9758358002],
        "pointstartp2": [-43.3718719482],
        "slopeendp1": [-144.545043945],
        "slopeendp2": [128.667724609],
        "slopeerrorp1": [0.173976004124],
        "slopeerrorp2": [0.0726276040077],
        "slopemiddlep1": [58.9801940918],
        "slopemiddlep2": [-45.1694297791],
        "slopestartp1": [-157.956466675],
        "slopestartp2": [159.690246582],
        "stddevp1": [2.84533977509],
        "stddevp2": [7.09442234039]
    },
    "mfcc3": {
        "ARc0p1": [19.4996566772],
        "ARc0p2": [0.00449076667428],
        "ARc1p1": [-1.17549435082e-38],
        "ARc1p2": [-1.17549435082e-38],
        "ARc2p1": [0.626447141171],
        "ARc2p2": [0.586875319481],
        "ARc3p1": [-1.17549435082e-38],
        "ARc3p2": [-1.17549435082e-38],
        "ARc4p1": [1.25228428841],
        "ARc4p2": [1.55561852455],
        "ARerrp1": [1.19461214542],
        "ARerrp2": [0.291019886732],
        "Accelerationp1": [510.415679932],
        "Accelerationp2": [43.9316673279],
        "Centroidp1": [0.54519110918],
        "Centroidp2": [0.0541754439473],
        "Derivativep1": [746.92376709],
        "Derivativep2": [57.6297111511],
        "Meanp1": [41.2838134766],
        "Meanp2": [4.22036123276],
        "Medianp1": [43.2290878296],
        "Medianp2": [8.01086425781e-05],
        "SpKurtp1": [1.62986183167],
        "SpKurtp2": [2.81084823608],
        "SpSkewp1": [1.63233602047],
        "SpSkewp2": [1.90131366253],
        "SpSpreadp1": [0.069609709084],
        "SpSpreadp2": [0.0542651899159],
        "pointdiffp1": [40.1432609558],
        "pointdiffp2": [-50.9778060913],
        "pointmiddlep1": [0.831884086132],
        "pointmiddlep2": [0.936038792133],
        "pointstartp1": [12.8853654861],
        "pointstartp2": [44.5203475952],
        "slopeendp1": [139.981781006],
        "slopeendp2": [-127.950508118],
        "slopeerrorp1": [0.0572355762124],
        "slopeerrorp2": [0.0663718059659],
        "slopemiddlep1": [-56.4546394348],
        "slopemiddlep2": [43.216796875],
        "slopestartp1": [159.02204895],
        "slopestartp2": [-159.523376465],
        "stddevp1": [6.87912368774],
        "stddevp2": [6.92467594147]
    },
    "mfcc4": {
        "ARc0p1": [-1.17549435082e-38],
        "ARc0p2": [0.008161239326],
        "ARc1p1": [0.136442273855],
        "ARc1p2": [0.0266649723053],
        "ARc2p1": [0.160004720092],
        "ARc2p2": [0.39471501112],
        "ARc3p1": [-1.17549435082e-38],
        "ARc3p2": [-1.17549435082e-38],
        "ARc4p1": [1.05554974079],
        "ARc4p2": [1.47173511982],
        "ARerrp1": [1.30356764793],
        "ARerrp2": [0.297689169645],
        "Accelerationp1": [651.952087402],
        "Accelerationp2": [47.6606025696],
        "Centroidp1": [0.543059766293],
        "Centroidp2": [-0.310770571232],
        "Derivativep1": [817.458557129],
        "Derivativep2": [61.4521064758],
        "Meanp1": [-26.8228759766],
        "Meanp2": [-0.140611767769],
        "Medianp1": [-29.0973930359],
        "Medianp2": [-6.103515625e-05],
        "SpKurtp1": [1.57536554337],
        "SpKurtp2": [1.14459896088],
        "SpSkewp1": [1.56526839733],
        "SpSkewp2": [1.34710633755],
        "SpSpreadp1": [0.0538594163954],
        "SpSpreadp2": [0.0544461794198],
        "pointdiffp1": [-12.1142053604],
        "pointdiffp2": [8.28555202484],
        "pointmiddlep1": [1.29770255089],
        "pointmiddlep2": [0.830526173115],
        "pointstartp1": [-14.726064682],
        "pointstartp2": [-6.10815095901],
        "slopeendp1": [132.899230957],
        "slopeendp2": [150.951156616],
        "slopeerrorp1": [0.315676033497],
        "slopeerrorp2": [0.234211504459],
        "slopemiddlep1": [-92.8895797729],
        "slopemiddlep2": [-94.9828033447],
        "slopestartp1": [-152.50491333],
        "slopestartp2": [162.519058228],
        "stddevp1": [5.21215820312],
        "stddevp2": [1.34536480904]
    },
    "mfcc5": {
        "ARc0p1": [-1.17549435082e-38],
        "ARc0p2": [-1.17549435082e-38],
        "ARc1p1": [0.0802771896124],
        "ARc1p2": [-1.17549435082e-38],
        "ARc2p1": [0.148043304682],
        "ARc2p2": [0.624412417412],
        "ARc3p1": [-1.17549435082e-38],
        "ARc3p2": [-1.17549435082e-38],
        "ARc4p1": [1.12680709362],
        "ARc4p2": [1.5485483408],
        "ARerrp1": [1.14691650867],
        "ARerrp2": [0.319533914328],
        "Accelerationp1": [766.650024414],
        "Accelerationp2": [52.4903793335],
        "Centroidp1": [0.541308224201],
        "Centroidp2": [0.0703073889017],
        "Derivativep1": [724.878540039],
        "Derivativep2": [68.0811843872],
        "Meanp1": [-27.1419086456],
        "Meanp2": [-3.20023703575],
        "Medianp1": [-27.9378967285],
        "Medianp2": [2.28881835938e-05],
        "SpKurtp1": [1.65791273117],
        "SpKurtp2": [1.31714773178],
        "SpSkewp1": [1.63425326347],
        "SpSkewp2": [1.46727597713],
        "SpSpreadp1": [0.0671411752701],
        "SpSpreadp2": [0.0585392825305],
        "pointdiffp1": [-21.0998687744],
        "pointdiffp2": [32.2559432983],
        "pointmiddlep1": [1.0839099884],
        "pointmiddlep2": [0.961132764816],
        "pointstartp1": [-8.8917131424],
        "pointstartp2": [-29.2391300201],
        "slopeendp1": [-105.069091797],
        "slopeendp2": [116.124023438],
        "slopeerrorp1": [0.160042569041],
        "slopeerrorp2": [0.058378316462],
        "slopemiddlep1": [35.5146217346],
        "slopemiddlep2": [-25.2905750275],
        "slopestartp1": [-161.00177002],
        "slopestartp2": [158.604156494],
        "stddevp1": [5.27784395218],
        "stddevp2": [5.10151481628]
    },
    "mfcc6": {
        "ARc0p1": [-1.17549435082e-38],
        "ARc0p2": [-1.17549435082e-38],
        "ARc1p1": [-1.17549435082e-38],
        "ARc1p2": [-1.17549435082e-38],
        "ARc2p1": [0.3629783988],
        "ARc2p2": [0.562380194664],
        "ARc3p1": [-1.17549435082e-38],
        "ARc3p2": [-1.17549435082e-38],
        "ARc4p1": [1.28708159924],
        "ARc4p2": [1.38482236862],
        "ARerrp1": [0.875441968441],
        "ARerrp2": [0.372305065393],
        "Accelerationp1": [244.311782837],
        "Accelerationp2": [50.8549957275],
        "Centroidp1": [0.548052668571],
        "Centroidp2": [0.0889447331429],
        "Derivativep1": [504.870269775],
        "Derivativep2": [69.9824829102],
        "Meanp1": [-14.0169448853],
        "Meanp2": [-1.38105928898],
        "Medianp1": [-14.8577270508],
        "Medianp2": [-2.67028808594e-05],
        "SpKurtp1": [4.19480514526],
        "SpKurtp2": [0.768572568893],
        "SpSkewp1": [2.08534097672],
        "SpSkewp2": [1.22770774364],
        "SpSpreadp1": [0.0494168400764],
        "SpSpreadp2": [0.0558916479349],
        "pointdiffp1": [-22.3933925629],
        "pointdiffp2": [11.9711809158],
        "pointmiddlep1": [1.11552286148],
        "pointmiddlep2": [0.9676399827],
        "pointstartp1": [5.79453468323],
        "pointstartp2": [-11.0968284607],
        "slopeendp1": [-139.04234314],
        "slopeendp2": [104.457939148],
        "slopeerrorp1": [0.0874944776297],
        "slopeerrorp2": [0.0799241960049],
        "slopemiddlep1": [93.8655700684],
        "slopemiddlep2": [-9.20992279053],
        "slopestartp1": [-165.012420654],
        "slopestartp2": [157.51940918],
        "stddevp1": [5.31679582596],
        "stddevp2": [2.19360351562]
    },
    "mfcc7": {
        "ARc0p1": [-1.17549435082e-38],
        "ARc0p2": [-1.17549435082e-38],
        "ARc1p1": [-1.17549435082e-38],
        "ARc1p2": [-1.17549435082e-38],
        "ARc2p1": [1.43595862389],
        "ARc2p2": [0.524464905262],
        "ARc3p1": [-1.17549435082e-38],
        "ARc3p2": [-1.17549435082e-38],
        "ARc4p1": [1.63979876041],
        "ARc4p2": [1.34877216816],
        "ARerrp1": [1.1455694437],
        "ARerrp2": [0.372162401676],
        "Accelerationp1": [553.968688965],
        "Accelerationp2": [62.7411994934],
        "Centroidp1": [0.577457368374],
        "Centroidp2": [0.0703523531556],
        "Derivativep1": [708.798583984],
        "Derivativep2": [68.419303894],
        "Meanp1": [-21.3221035004],
        "Meanp2": [-2.81764650345],
        "Medianp1": [-22.8349075317],
        "Medianp2": [-5.34057617188e-05],
        "SpKurtp1": [3.80619573593],
        "SpKurtp2": [1.91098690033],
        "SpSkewp1": [2.03024411201],
        "SpSkewp2": [1.61081171036],
        "SpSpreadp1": [0.0480756647885],
        "SpSpreadp2": [0.0524688884616],
        "pointdiffp1": [-27.4217605591],
        "pointdiffp2": [29.3127326965],
        "pointmiddlep1": [1.3024841547],
        "pointmiddlep2": [0.950968444347],
        "pointstartp1": [6.14223384857],
        "pointstartp2": [-26.2821445465],
        "slopeendp1": [3.48944544792],
        "slopeendp2": [119.790916443],
        "slopeerrorp1": [0.133216693997],
        "slopeerrorp2": [0.0542426817119],
        "slopemiddlep1": [10.2557706833],
        "slopemiddlep2": [-29.6113033295],
        "slopestartp1": [-162.210372925],
        "slopestartp2": [158.758102417],
        "stddevp1": [8.6550693512],
        "stddevp2": [4.36292886734]
    },
    "mfcc8": {
        "ARc0p1": [-1.17549435082e-38],
        "ARc0p2": [-1.17549435082e-38],
        "ARc1p1": [-1.17549435082e-38],
        "ARc1p2": [0.0131245777011],
        "ARc2p1": [1.23289692402],
        "ARc2p2": [0.422676354647],
        "ARc3p1": [-1.17549435082e-38],
        "ARc3p2": [-1.17549435082e-38],
        "ARc4p1": [1.47986316681],
        "ARc4p2": [1.28910911083],
        "ARerrp1": [1.37683904171],
        "ARerrp2": [0.383791565895],
        "Accelerationp1": [569.376342773],
        "Accelerationp2": [61.0045700073],
        "Centroidp1": [0.680807113647],
        "Centroidp2": [0.0805471614003],
        "Derivativep1": [706.884094238],
        "Derivativep2": [72.8733520508],
        "Meanp1": [-19.5604476929],
        "Meanp2": [-3.44846773148],
        "Medianp1": [-25.5543708801],
        "Medianp2": [-4.57763671875e-05],
        "SpKurtp1": [3.07840251923],
        "SpKurtp2": [1.20860147476],
        "SpSkewp1": [1.90904152393],
        "SpSkewp2": [1.4302970171],
        "SpSpreadp1": [0.0563611350954],
        "SpSpreadp2": [0.0595108680427],
        "pointdiffp1": [-32.7604446411],
        "pointdiffp2": [30.9193477631],
        "pointmiddlep1": [1.12566876411],
        "pointmiddlep2": [0.97698444128],
        "pointstartp1": [9.63051795959],
        "pointstartp2": [-28.7350139618],
        "slopeendp1": [135.201766968],
        "slopeendp2": [104.502403259],
        "slopeerrorp1": [0.0793382301927],
        "slopeerrorp2": [0.05790354684],
        "slopemiddlep1": [-111.248962402],
        "slopemiddlep2": [-11.3929357529],
        "slopestartp1": [-137.614654541],
        "slopestartp2": [157.844711304],
        "stddevp1": [11.9088439941],
        "stddevp2": [5.37631464005]
    },
    "mfcc9": {
        "ARc0p1": [0.0467831715941],
        "ARc0p2": [-1.17549435082e-38],
        "ARc1p1": [0.267160624266],
        "ARc1p2": [0.0202639065683],
        "ARc2p1": [0.0905245989561],
        "ARc2p2": [0.411621898413],
        "ARc3p1": [-1.17549435082e-38],
        "ARc3p2": [-1.17549435082e-38],
        "ARc4p1": [1.18851542473],
        "ARc4p2": [1.45173001289],
        "ARerrp1": [0.879293680191],
        "ARerrp2": [0.412199497223],
        "Accelerationp1": [190.501068115],
        "Accelerationp2": [60.8253059387],
        "Centroidp1": [0.570676922798],
        "Centroidp2": [0.0806337594986],
        "Derivativep1": [346.093414307],
        "Derivativep2": [75.1692962646],
        "Meanp1": [-13.5112133026],
        "Meanp2": [-1.73703086376],
        "Medianp1": [-13.8624191284],
        "Medianp2": [-2.28881835938e-05],
        "SpKurtp1": [1.5901632309],
        "SpKurtp2": [1.07317686081],
        "SpSkewp1": [1.59566926956],
        "SpSkewp2": [1.30081522465],
        "SpSpreadp1": [0.0735719203949],
        "SpSpreadp2": [0.0554879270494],
        "pointdiffp1": [-13.8743133545],
        "pointdiffp2": [16.2019252777],
        "pointmiddlep1": [0.487690001726],
        "pointmiddlep2": [0.96355342865],
        "pointstartp1": [-6.68080329895],
        "pointstartp2": [-14.8423366547],
        "slopeendp1": [-138.929977417],
        "slopeendp2": [110.986053467],
        "slopeerrorp1": [0.147080823779],
        "slopeerrorp2": [0.0650574713945],
        "slopemiddlep1": [-21.4956703186],
        "slopemiddlep2": [-17.5561923981],
        "slopestartp1": [-137.495010376],
        "slopestartp2": [158.077514648],
        "stddevp1": [3.3343963623],
        "stddevp2": [2.6825003624]
    },
    "pitchSalience": {
        "ARc0p1": [0.0914782360196],
        "ARc0p2": [0.026229986921],
        "ARc1p1": [0.291776925325],
        "ARc1p2": [0.15789681673],
        "ARc2p1": [0.076995626092],
        "ARc2p2": [0.203144267201],
        "ARc3p1": [-1.17549435082e-38],
        "ARc3p2": [-1.17549435082e-38],
        "ARc4p1": [0.803546845913],
        "ARc4p2": [1.06340706348],
        "ARerrp1": [0.0190031379461],
        "ARerrp2": [0.0327856913209],
        "Accelerationp1": [4.91303014755],
        "Accelerationp2": [5.64534187317],
        "Centroidp1": [0.451750934124],
        "Centroidp2": [0.513208508492],
        "Derivativep1": [6.1151843071],
        "Derivativep2": [6.43016433716],
        "Meanp1": [0.651494145393],
        "Meanp2": [0.603838026524],
        "Medianp1": [0.609187662601],
        "Medianp2": [0.595558047295],
        "SpKurtp1": [0.35080909729],
        "SpKurtp2": [1.51739740372],
        "SpSkewp1": [1.34304964542],
        "SpSkewp2": [1.56168532372],
        "SpSpreadp1": [0.100751556456],
        "SpSpreadp2": [0.0606105923653],
        "pointdiffp1": [-0.314843922853],
        "pointdiffp2": [0.0361722931266],
        "pointmiddlep1": [0.697438120842],
        "pointmiddlep2": [-0.768862903118],
        "pointstartp1": [0.847767531872],
        "pointstartp2": [0.616334497929],
        "slopeendp1": [21.0404434204],
        "slopeendp2": [-130.171905518],
        "slopeerrorp1": [0.0828087851405],
        "slopeerrorp2": [1.93563020229],
        "slopemiddlep1": [-100.294075012],
        "slopemiddlep2": [157.873184204],
        "slopestartp1": [-108.684425354],
        "slopestartp2": [-170.707611084],
        "stddevp1": [0.0997309759259],
        "stddevp2": [0.0768011286855]
    },
    "pitchYin-st": {
        "ARc0p1": [4729.20800781],
        "ARc0p2": [102.374053955],
        "ARc1p1": [-1.17549435082e-38],
        "ARc1p2": [0.183291584253],
        "ARc2p1": [-1.17549435082e-38],
        "ARc2p2": [0.0714439749718],
        "ARc3p1": [-1.17549435082e-38],
        "ARc3p2": [0.034389320761],
        "ARc4p1": [0.0545743852854],
        "ARc4p2": [0.649838328362],
        "ARerrp1": [434.05291748],
        "ARerrp2": [336.126312256],
        "Accelerationp1": [109.692398071],
        "Accelerationp2": [91.8691101074],
        "Centroidp1": [-48.0150299072],
        "Centroidp2": [-46.4300193787],
        "Derivativep1": [102.181152344],
        "Derivativep2": [87.5673065186],
        "Meanp1": [53.4482078552],
        "Meanp2": [49.471031189],
        "Medianp1": [45.7944564819],
        "Medianp2": [31.0756778717],
        "SpKurtp1": [-0.380797147751],
        "SpKurtp2": [-0.741806268692],
        "SpSkewp1": [0.983172953129],
        "SpSkewp2": [0.715842723846],
        "SpSpreadp1": [0.0877985656261],
        "SpSpreadp2": [0.0893910899758],
        "pointdiffp1": [2029.67565918],
        "pointdiffp2": [-1793.59765625],
        "pointmiddlep1": [0.751618266106],
        "pointmiddlep2": [2.25376605988],
        "pointstartp1": [1084.20373535],
        "pointstartp2": [4728.76269531],
        "slopeendp1": [157.213378906],
        "slopeendp2": [-152.323974609],
        "slopeerrorp1": [0.542410314083],
        "slopeerrorp2": [0.464078396559],
        "slopemiddlep1": [-112.065681458],
        "slopemiddlep2": [152.17741394],
        "slopestartp1": [163.683517456],
        "slopestartp2": [-173.67250061],
        "stddevp1": [53.1800041199],
        "stddevp2": [49.1367607117]
    },
    "pitchYinConfidence": {
        "ARc0p1": [0.175731062889],
        "ARc0p2": [0.0280709359795],
        "ARc1p1": [-1.17549435082e-38],
        "ARc1p2": [0.0963135063648],
        "ARc2p1": [0.705282330513],
        "ARc2p2": [0.209887340665],
        "ARc3p1": [-1.17549435082e-38],
        "ARc3p2": [-1.17549435082e-38],
        "ARc4p1": [1.36691236496],
        "ARc4p2": [1.0703305006],
        "ARerrp1": [0.0172875747085],
        "ARerrp2": [0.0388764329255],
        "Accelerationp1": [6.51274347305],
        "Accelerationp2": [6.27313232422],
        "Centroidp1": [0.569925487041],
        "Centroidp2": [0.526653647423],
        "Derivativep1": [7.2218708992],
        "Derivativep2": [7.33338546753],
        "Meanp1": [0.574343442917],
        "Meanp2": [0.448526412249],
        "Medianp1": [0.638350427151],
        "Medianp2": [0.436249375343],
        "SpKurtp1": [1.32508325577],
        "SpKurtp2": [0.772346496582],
        "SpSkewp1": [1.62083518505],
        "SpSkewp2": [1.29513823986],
        "SpSpreadp1": [0.0824703127146],
        "SpSpreadp2": [0.0639897286892],
        "pointdiffp1": [0.305766224861],
        "pointdiffp2": [-0.194996625185],
        "pointmiddlep1": [0.998413443565],
        "pointmiddlep2": [0.94042289257],
        "pointstartp1": [0.326211541891],
        "pointstartp2": [0.603248417377],
        "slopeendp1": [-147.564743042],
        "slopeendp2": [-165.620223999],
        "slopeerrorp1": [0.117309875786],
        "slopeerrorp2": [0.371565878391],
        "slopemiddlep1": [131.544158936],
        "slopemiddlep2": [146.704544067],
        "slopestartp1": [57.5602645874],
        "slopestartp2": [-170.018081665],
        "stddevp1": [0.133982270956],
        "stddevp2": [0.101438350976]
    },
    "spectral_crest": {
        "ARc0p1": [2.73760986328],
        "ARc0p2": [0.0610003769398],
        "ARc1p1": [0.283598035574],
        "ARc1p2": [0.0675503611565],
        "ARc2p1": [0.19363245368],
        "ARc2p2": [0.312628537416],
        "ARc3p1": [0.0316783711314],
        "ARc3p2": [-1.17549435082e-38],
        "ARc4p1": [-1.17549435082e-38],
        "ARc4p2": [1.62626230717],
        "ARerrp1": [0.113550916314],
        "ARerrp2": [0.347417712212],
        "Accelerationp1": [78.4760742188],
        "Accelerationp2": [59.331325531],
        "Centroidp1": [0.409416347742],
        "Centroidp2": [0.593114495277],
        "Derivativep1": [91.2776412964],
        "Derivativep2": [77.0911483765],
        "Meanp1": [7.88045454025],
        "Meanp2": [18.9347057343],
        "Medianp1": [6.65857553482],
        "Medianp2": [23.7818088531],
        "SpKurtp1": [0.471913337708],
        "SpKurtp2": [8.21764755249],
        "SpSkewp1": [1.33896827698],
        "SpSkewp2": [2.78619503975],
        "SpSpreadp1": [0.0910140872002],
        "SpSpreadp2": [0.0273758415133],
        "pointdiffp1": [-7.81127691269],
        "pointdiffp2": [11.5692596436],
        "pointmiddlep1": [0.810453176498],
        "pointmiddlep2": [1.708522439],
        "pointstartp1": [13.3017416],
        "pointstartp2": [3.83386087418],
        "slopeendp1": [10.0706005096],
        "slopeendp2": [-165.705963135],
        "slopeerrorp1": [0.0437836721539],
        "slopeerrorp2": [0.174585193396],
        "slopemiddlep1": [-85.4235305786],
        "slopemiddlep2": [143.919891357],
        "slopestartp1": [-134.684692383],
        "slopestartp2": [118.875564575],
        "stddevp1": [2.13385295868],
        "stddevp2": [7.30757141113]
    },
    "spectral_flatness_db": {
        "ARc0p1": [0.0645628273487],
        "ARc0p2": [0.00409823376685],
        "ARc1p1": [0.060961805284],
        "ARc1p2": [-1.17549435082e-38],
        "ARc2p1": [0.543450474739],
        "ARc2p2": [0.411816745996],
        "ARc3p1": [-1.17549435082e-38],
        "ARc3p2": [-1.17549435082e-38],
        "ARc4p1": [0.592193424702],
        "ARc4p2": [1.79079401493],
        "ARerrp1": [0.00100010819733],
        "ARerrp2": [0.00518112396821],
        "Accelerationp1": [0.465243816376],
        "Accelerationp2": [0.836706221104],
        "Centroidp1": [0.468362212181],
        "Centroidp2": [0.573081552982],
        "Derivativep1": [0.683010518551],
        "Derivativep2": [1.1022695303],
        "Meanp1": [0.150365367532],
        "Meanp2": [0.201529622078],
        "Medianp1": [0.141956180334],
        "Medianp2": [0.206038340926],
        "SpKurtp1": [0.304584264755],
        "SpKurtp2": [6.91697216034],
        "SpSkewp1": [1.32104218006],
        "SpSkewp2": [2.50558114052],
        "SpSpreadp1": [0.0990472957492],
        "SpSpreadp2": [0.0292872749269],
        "pointdiffp1": [-0.0591817833483],
        "pointdiffp2": [0.0731018707156],
        "pointmiddlep1": [0.837230682373],
        "pointmiddlep2": [1.10247993469],
        "pointstartp1": [0.192429959774],
        "pointstartp2": [0.135632559657],
        "slopeendp1": [-54.9597015381],
        "slopeendp2": [-166.576004028],
        "slopeerrorp1": [0.0323881134391],
        "slopeerrorp2": [0.287546336651],
        "slopemiddlep1": [-58.9747848511],
        "slopemiddlep2": [155.175140381],
        "slopestartp1": [-145.474746704],
        "slopestartp2": [-149.571853638],
        "stddevp1": [0.0139023950323],
        "stddevp2": [0.0604873485863]
    },
    "tristimulus0": {
        "ARc0p1": [0.000380887300707],
        "ARc0p2": [0.00271007604897],
        "ARc1p1": [-1.17549435082e-38],
        "ARc1p2": [-1.17549435082e-38],
        "ARc2p1": [0.547964215279],
        "ARc2p2": [0.0117824226618],
        "ARc3p1": [-1.17549435082e-38],
        "ARc3p2": [0.0832779929042],
        "ARc4p1": [0.555884957314],
        "ARc4p2": [0.816188216209],
        "ARerrp1": [0.000425269419793],
        "ARerrp2": [0.0154776936397],
        "Accelerationp1": [0.170737951994],
        "Accelerationp2": [2.58714389801],
        "Centroidp1": [0.224230200052],
        "Centroidp2": [0.764919996262],
        "Derivativep1": [0.211468920112],
        "Derivativep2": [2.56882619858],
        "Meanp1": [0.00250843958929],
        "Meanp2": [0.0189637113363],
        "Medianp1": [0.000956754724029],
        "Medianp2": [0.00516572874039],
        "SpKurtp1": [2.46344995499],
        "SpKurtp2": [-0.0972521305084],
        "SpSkewp1": [1.61283516884],
        "SpSkewp2": [1.07561647892],
        "SpSpreadp1": [0.0528815500438],
        "SpSpreadp2": [0.0785481408238],
        "pointdiffp1": [-0.00590790435672],
        "pointdiffp2": [0.101787291467],
        "pointmiddlep1": [0.996615886688],
        "pointmiddlep2": [0.210298329592],
        "pointstartp1": [0.00729611655697],
        "pointstartp2": [-0.0122816935182],
        "slopeendp1": [136.459014893],
        "slopeendp2": [153.23890686],
        "slopeerrorp1": [0.203940406442],
        "slopeerrorp2": [0.211126148701],
        "slopemiddlep1": [-120.755485535],
        "slopemiddlep2": [-2.57697820663],
        "slopestartp1": [-111.513053894],
        "slopestartp2": [124.137863159],
        "stddevp1": [0.00251620309427],
        "stddevp2": [0.0230053868145]
    },
    "tristimulus1": {
        "ARc0p1": [0.133808001876],
        "ARc0p2": [0.0159694589674],
        "ARc1p1": [-1.17549435082e-38],
        "ARc1p2": [0.22523291409],
        "ARc2p1": [-1.17549435082e-38],
        "ARc2p2": [0.0467432141304],
        "ARc3p1": [-1.17549435082e-38],
        "ARc3p2": [0.113852106035],
        "ARc4p1": [-1.17549435082e-38],
        "ARc4p2": [0.508918106556],
        "ARerrp1": [0.00510159600526],
        "ARerrp2": [0.0253253765404],
        "Accelerationp1": [2.29975605011],
        "Accelerationp2": [3.90967082977],
        "Centroidp1": [0.499948352575],
        "Centroidp2": [0.525894582272],
        "Derivativep1": [2.01671242714],
        "Derivativep2": [4.85429191589],
        "Meanp1": [0.0697036013007],
        "Meanp2": [0.152113780379],
        "Medianp1": [0.0686659738421],
        "Medianp2": [0.152241453528],
        "SpKurtp1": [-0.0878427028656],
        "SpKurtp2": [-0.906872749329],
        "SpSkewp1": [1.20076799393],
        "SpSkewp2": [0.670244753361],
        "SpSpreadp1": [0.102982886136],
        "SpSpreadp2": [0.0993962809443],
        "pointdiffp1": [-0.000140265823575],
        "pointdiffp2": [-0.0356957502663],
        "pointmiddlep1": [-25.5174388885],
        "pointmiddlep2": [-3.2546210289],
        "pointstartp1": [0.0674928948283],
        "pointstartp2": [0.0806595161557],
        "slopeendp1": [-178.954208374],
        "slopeendp2": [-175.858261108],
        "slopeerrorp1": [68.9229812622],
        "slopeerrorp2": [0.776991903782],
        "slopemiddlep1": [100.975593567],
        "slopemiddlep2": [156.540603638],
        "slopestartp1": [178.839096069],
        "slopestartp2": [134.526779175],
        "stddevp1": [0.00948692392558],
        "stddevp2": [0.0474014393985]
    },
    "tristimulus2": {
        "ARc0p1": [1.76236951351],
        "ARc0p2": [0.0182805936784],
        "ARc1p1": [-1.17549435082e-38],
        "ARc1p2": [0.239409923553],
        "ARc2p1": [-1.17549435082e-38],
        "ARc2p2": [-1.17549435082e-38],
        "ARc3p1": [-1.17549435082e-38],
        "ARc3p2": [0.0136456778273],
        "ARc4p1": [-1.17549435082e-38],
        "ARc4p2": [0.755534887314],
        "ARerrp1": [0.0055080819875],
        "ARerrp2": [0.0301700141281],
        "Accelerationp1": [2.17939519882],
        "Accelerationp2": [4.50480270386],
        "Centroidp1": [0.500749468803],
        "Centroidp2": [0.477390259504],
        "Derivativep1": [1.99308753014],
        "Derivativep2": [5.5060043335],
        "Meanp1": [0.92778801918],
        "Meanp2": [0.809837162495],
        "Medianp1": [0.930852115154],
        "Medianp2": [0.82670789957],
        "SpKurtp1": [0.499514102936],
        "SpKurtp2": [1.48922348022],
        "SpSkewp1": [1.39985358715],
        "SpSkewp2": [1.61581325531],
        "SpSpreadp1": [0.0981935709715],
        "SpSpreadp2": [0.0688432082534],
        "pointdiffp1": [0.00604821229354],
        "pointdiffp2": [-0.412347048521],
        "pointmiddlep1": [0.381720721722],
        "pointmiddlep2": [0.428193092346],
        "pointstartp1": [0.925210952759],
        "pointstartp2": [0.996281445026],
        "slopeendp1": [10.6942825317],
        "slopeendp2": [-149.192199707],
        "slopeerrorp1": [1.46328282356],
        "slopeerrorp2": [0.169945463538],
        "slopemiddlep1": [118.766395569],
        "slopemiddlep2": [19.4192123413],
        "slopestartp1": [-80.9046554565],
        "slopestartp2": [-143.75050354],
        "stddevp1": [0.00895038433373],
        "stddevp2": [0.0715045630932]
    }
},
"slice": {
    "time": [[0, 11.0850114822]]
},
"Class": {
    "type0": "Cymbal",
    "type1": "Ride",
    "type2": "r20",
    "type3": "CshRd",
    "type4": "none"
},
"audiopath": "\/Users\/mhermant\/Documents\/Work\/Datasets\/DrumKitFromHell\/Cymbal.Ride.r20 CshRd R03   x.wav"
}