{
"metadata": {
    "version": {
        "essentia": "2.1-beta2"
    }
},
"values": {
    "barkbands_kurtosis": {
        "ARc0p1": [-1.17549435082e-38],
        "ARc0p2": [20.521030426],
        "ARc1p1": [0.112718708813],
        "ARc1p2": [0.0889773219824],
        "ARc2p1": [0.288774013519],
        "ARc2p2": [0.0107748443261],
        "ARc3p1": [-1.17549435082e-38],
        "ARc3p2": [-1.17549435082e-38],
        "ARc4p1": [1.69418549538],
        "ARc4p2": [0.376163512468],
        "ARerrp1": [0.123155705631],
        "ARerrp2": [25.2868881226],
        "Accelerationp1": [38.7980651855],
        "Accelerationp2": [2842.13452148],
        "Centroidp1": [-0.33226442337],
        "Centroidp2": [0.765290856361],
        "Derivativep1": [51.0881080627],
        "Derivativep2": [3461.68701172],
        "Meanp1": [0.282911866903],
        "Meanp2": [38.0123291016],
        "Medianp1": [-0.215627670288],
        "Medianp2": [14.7817020416],
        "SpKurtp1": [0.371987581253],
        "SpKurtp2": [-1.08372795582],
        "SpSkewp1": [1.06514585018],
        "SpSkewp2": [0.318163514137],
        "SpSpreadp1": [0.0648703202605],
        "SpSpreadp2": [0.0851337462664],
        "pointdiffp1": [-2.00371456146],
        "pointdiffp2": [122.161468506],
        "pointmiddlep1": [0.627187430859],
        "pointmiddlep2": [0.177359968424],
        "pointstartp1": [1.4440485239],
        "pointstartp2": [3.1738615036],
        "slopeendp1": [92.9882965088],
        "slopeendp2": [133.908004761],
        "slopeerrorp1": [0.168174698949],
        "slopeerrorp2": [0.254447758198],
        "slopemiddlep1": [-121.136634827],
        "slopemiddlep2": [88.2550430298],
        "slopestartp1": [4.13026714325],
        "slopestartp2": [-25.9651241302],
        "stddevp1": [0.810146212578],
        "stddevp2": [37.3469657898]
    },
    "barkbands_skewness": {
        "ARc0p1": [-1.17549435082e-38],
        "ARc0p2": [0.539892017841],
        "ARc1p1": [-1.17549435082e-38],
        "ARc1p2": [0.161413788795],
        "ARc2p1": [0.665233671665],
        "ARc2p2": [0.0149913439527],
        "ARc3p1": [-1.17549435082e-38],
        "ARc3p2": [-1.17549435082e-38],
        "ARc4p1": [1.76420617104],
        "ARc4p2": [0.861812889576],
        "ARerrp1": [0.0427373796701],
        "ARerrp2": [0.637010037899],
        "Accelerationp1": [12.0559358597],
        "Accelerationp2": [62.708366394],
        "Centroidp1": [0.40597859025],
        "Centroidp2": [0.646326839924],
        "Derivativep1": [14.5631427765],
        "Derivativep2": [91.283203125],
        "Meanp1": [0.898690342903],
        "Meanp2": [4.13546800613],
        "Medianp1": [0.857467412949],
        "Medianp2": [3.48853445053],
        "SpKurtp1": [1.18199634552],
        "SpKurtp2": [-0.281388282776],
        "SpSkewp1": [1.54108655453],
        "SpSkewp2": [0.900772452354],
        "SpSpreadp1": [0.0803551226854],
        "SpSpreadp2": [0.076863899827],
        "pointdiffp1": [-0.817480385303],
        "pointdiffp2": [0.836048305035],
        "pointmiddlep1": [0.382291316986],
        "pointmiddlep2": [2.84788513184],
        "pointstartp1": [1.24729013443],
        "pointstartp2": [2.41050004959],
        "slopeendp1": [-80.4578399658],
        "slopeendp2": [-177.555496216],
        "slopeerrorp1": [0.0999972000718],
        "slopeerrorp2": [1.39215695858],
        "slopemiddlep1": [-105.390609741],
        "slopemiddlep2": [174.341552734],
        "slopestartp1": [10.9380989075],
        "slopestartp2": [-175.920562744],
        "stddevp1": [0.257331907749],
        "stddevp2": [2.78403735161]
    },
    "barkbands_spread": {
        "ARc0p1": [3.60901689529],
        "ARc0p2": [0.843122839928],
        "ARc1p1": [-1.17549435082e-38],
        "ARc1p2": [-1.17549435082e-38],
        "ARc2p1": [0.696682393551],
        "ARc2p2": [0.70263248682],
        "ARc3p1": [-1.17549435082e-38],
        "ARc3p2": [-1.17549435082e-38],
        "ARc4p1": [1.98929774761],
        "ARc4p2": [1.82643198967],
        "ARerrp1": [0.668482005596],
        "ARerrp2": [1.08266997337],
        "Accelerationp1": [181.572753906],
        "Accelerationp2": [166.979873657],
        "Centroidp1": [0.564307391644],
        "Centroidp2": [0.524758219719],
        "Derivativep1": [299.218688965],
        "Derivativep2": [264.965026855],
        "Meanp1": [23.9646263123],
        "Meanp2": [14.3590898514],
        "Medianp1": [25.9968204498],
        "Medianp2": [10.8687810898],
        "SpKurtp1": [1.22351408005],
        "SpKurtp2": [3.02976036072],
        "SpSkewp1": [1.60517048836],
        "SpSkewp2": [1.86262071133],
        "SpSpreadp1": [0.0852287486196],
        "SpSpreadp2": [0.0456349700689],
        "pointdiffp1": [12.3615131378],
        "pointdiffp2": [29.9090747833],
        "pointmiddlep1": [1.16539931297],
        "pointmiddlep2": [-0.119577936828],
        "pointstartp1": [12.643029213],
        "pointstartp2": [11.7426347733],
        "slopeendp1": [-149.531433105],
        "slopeendp2": [165.358703613],
        "slopeerrorp1": [0.135032042861],
        "slopeerrorp2": [0.164893627167],
        "slopemiddlep1": [126.987640381],
        "slopemiddlep2": [-98.1126480103],
        "slopestartp1": [117.605079651],
        "slopestartp2": [141.039718628],
        "stddevp1": [5.5917134285],
        "stddevp2": [7.187520504]
    },
    "envelope": {
        "ARc0p1": [5.62994000575e-06],
        "ARc0p2": [-1.17549435082e-38],
        "ARc1p1": [-1.17549435082e-38],
        "ARc1p2": [-1.17549435082e-38],
        "ARc2p1": [1.06119942665],
        "ARc2p2": [1.08363211155],
        "ARc3p1": [-1.17549435082e-38],
        "ARc3p2": [-1.17549435082e-38],
        "ARc4p1": [2.47720527649],
        "ARc4p2": [2.33752417564],
        "ARerrp1": [1.46038319144e-05],
        "ARerrp2": [5.07317432508e-09],
        "Accelerationp1": [0.631624221802],
        "Accelerationp2": [0.000195999033167],
        "Centroidp1": [0.635416865349],
        "Centroidp2": [0.280943125486],
        "Derivativep1": [1.92093992233],
        "Derivativep2": [0.0384140014648],
        "Meanp1": [0.13086771965],
        "Meanp2": [0.0586150214076],
        "Medianp1": [0.174031496048],
        "Medianp2": [0.0413033030927],
        "SpKurtp1": [7.50517368317],
        "SpKurtp2": [8.05503463745],
        "SpSkewp1": [2.83244347572],
        "SpSkewp2": [2.91893005371],
        "SpSpreadp1": [0.0385323278606],
        "SpSpreadp2": [0.0370769873261],
        "pointdiffp1": [0.215395107865],
        "pointdiffp2": [-0.174249723554],
        "pointmiddlep1": [0.988289117813],
        "pointmiddlep2": [0.810177147388],
        "pointstartp1": [-0.046930514276],
        "pointstartp2": [0.181770592928],
        "slopeendp1": [-83.170539856],
        "slopeendp2": [-37.3505821228],
        "slopeerrorp1": [0.0584549792111],
        "slopeerrorp2": [0.00297311251052],
        "slopemiddlep1": [88.0845718384],
        "slopemiddlep2": [-70.7990188599],
        "slopestartp1": [143.346450806],
        "slopestartp2": [-140.943069458],
        "stddevp1": [0.0605776011944],
        "stddevp2": [0.0393955819309]
    },
    "mfcc0": {
        "ARc0p1": [-1.17549435082e-38],
        "ARc0p2": [-1.17549435082e-38],
        "ARc1p1": [-1.17549435082e-38],
        "ARc1p2": [-1.17549435082e-38],
        "ARc2p1": [0.080100685358],
        "ARc2p2": [0.731769323349],
        "ARc3p1": [-1.17549435082e-38],
        "ARc3p2": [-1.17549435082e-38],
        "ARc4p1": [1.60181379318],
        "ARc4p2": [1.50524652004],
        "ARerrp1": [2.57859921455],
        "ARerrp2": [0.457893550396],
        "Accelerationp1": [2651.55664062],
        "Accelerationp2": [87.7205657959],
        "Centroidp1": [0.472649216652],
        "Centroidp2": [0.509963870049],
        "Derivativep1": [6601.24121094],
        "Derivativep2": [138.528457642],
        "Meanp1": [-684.47869873],
        "Meanp2": [-1113.54455566],
        "Medianp1": [-644.339172363],
        "Medianp2": [-1138.42004395],
        "SpKurtp1": [-0.451959609985],
        "SpKurtp2": [2.34868907928],
        "SpSkewp1": [1.03744649887],
        "SpSkewp2": [1.91139245033],
        "SpSpreadp1": [0.114521928132],
        "SpSpreadp2": [0.0685094967484],
        "pointdiffp1": [408.590240479],
        "pointdiffp2": [-302.924530029],
        "pointmiddlep1": [1.20908987522],
        "pointmiddlep2": [0.933176040649],
        "pointstartp1": [-1069.85339355],
        "pointstartp2": [-874.711853027],
        "slopeendp1": [104.000335693],
        "slopeendp2": [-128.773574829],
        "slopeerrorp1": [0.0573302768171],
        "slopeerrorp2": [0.0650867596269],
        "slopemiddlep1": [-58.3362045288],
        "slopemiddlep2": [44.5190429688],
        "slopestartp1": [163.631225586],
        "slopestartp2": [-159.577423096],
        "stddevp1": [85.4323425293],
        "stddevp2": [39.9861679077]
    },
    "mfcc1": {
        "ARc0p1": [-1.17549435082e-38],
        "ARc0p2": [-1.17549435082e-38],
        "ARc1p1": [-1.17549435082e-38],
        "ARc1p2": [-1.17549435082e-38],
        "ARc2p1": [0.694927453995],
        "ARc2p2": [0.831725895405],
        "ARc3p1": [-1.17549435082e-38],
        "ARc3p2": [-1.17549435082e-38],
        "ARc4p1": [1.02147436142],
        "ARc4p2": [1.58904445171],
        "ARerrp1": [1.74266755581],
        "ARerrp2": [0.510676562786],
        "Accelerationp1": [1335.71569824],
        "Accelerationp2": [86.4082107544],
        "Centroidp1": [0.423450350761],
        "Centroidp2": [0.0859343409538],
        "Derivativep1": [1603.8170166],
        "Derivativep2": [112.352546692],
        "Meanp1": [61.6127853394],
        "Meanp2": [9.57570552826],
        "Medianp1": [57.967010498],
        "Medianp2": [1.14440917969e-05],
        "SpKurtp1": [2.98835039139],
        "SpKurtp2": [3.83442926407],
        "SpSkewp1": [1.88541853428],
        "SpSkewp2": [2.1358692646],
        "SpSpreadp1": [0.042579639703],
        "SpSpreadp2": [0.0459761545062],
        "pointdiffp1": [-7.91128063202],
        "pointdiffp2": [-82.3302993774],
        "pointmiddlep1": [-3.34544014931],
        "pointmiddlep2": [0.977381765842],
        "pointstartp1": [46.5544548035],
        "pointstartp2": [76.9090957642],
        "slopeendp1": [172.972137451],
        "slopeendp2": [-101.160522461],
        "slopeerrorp1": [1.19477856159],
        "slopeerrorp2": [0.048613935709],
        "slopemiddlep1": [-173.396652222],
        "slopemiddlep2": [7.21462154388],
        "slopestartp1": [177.565383911],
        "slopestartp2": [-157.536651611],
        "stddevp1": [21.8346405029],
        "stddevp2": [14.3231992722]
    },
    "mfcc10": {
        "ARc0p1": [-1.17549435082e-38],
        "ARc0p2": [-1.17549435082e-38],
        "ARc1p1": [0.006382628344],
        "ARc1p2": [-1.17549435082e-38],
        "ARc2p1": [-1.17549435082e-38],
        "ARc2p2": [0.769909501076],
        "ARc3p1": [-1.17549435082e-38],
        "ARc3p2": [-1.17549435082e-38],
        "ARc4p1": [0.775669276714],
        "ARc4p2": [1.46280837059],
        "ARerrp1": [1.17107903957],
        "ARerrp2": [0.447725206614],
        "Accelerationp1": [615.433044434],
        "Accelerationp2": [73.5049209595],
        "Centroidp1": [0.528177976608],
        "Centroidp2": [0.10619160533],
        "Derivativep1": [744.166870117],
        "Derivativep2": [88.5428085327],
        "Meanp1": [-23.6452331543],
        "Meanp2": [-4.54822778702],
        "Medianp1": [-23.5931892395],
        "Medianp2": [-2.67028808594e-05],
        "SpKurtp1": [4.47998571396],
        "SpKurtp2": [2.04670619965],
        "SpSkewp1": [2.21769976616],
        "SpSkewp2": [1.67529606819],
        "SpSpreadp1": [0.046179689467],
        "SpSpreadp2": [0.0520221032202],
        "pointdiffp1": [-12.3235006332],
        "pointdiffp2": [31.1788349152],
        "pointmiddlep1": [1.59318828583],
        "pointmiddlep2": [1.00108397007],
        "pointstartp1": [-9.063539505],
        "pointstartp2": [-30.5397129059],
        "slopeendp1": [76.8027877808],
        "slopeendp2": [58.8242149353],
        "slopeerrorp1": [0.397456616163],
        "slopeerrorp2": [0.052497446537],
        "slopemiddlep1": [32.3511695862],
        "slopemiddlep2": [24.3727931976],
        "slopestartp1": [-165.66708374],
        "slopestartp2": [155.327636719],
        "stddevp1": [6.02595376968],
        "stddevp2": [6.56785869598]
    },
    "mfcc11": {
        "ARc0p1": [-1.17549435082e-38],
        "ARc0p2": [-1.17549435082e-38],
        "ARc1p1": [-1.17549435082e-38],
        "ARc1p2": [-1.17549435082e-38],
        "ARc2p1": [0.556157886982],
        "ARc2p2": [0.569324076176],
        "ARc3p1": [-1.17549435082e-38],
        "ARc3p2": [-1.17549435082e-38],
        "ARc4p1": [1.19894897938],
        "ARc4p2": [1.43879449368],
        "ARerrp1": [1.97316336632],
        "ARerrp2": [0.519774198532],
        "Accelerationp1": [454.127075195],
        "Accelerationp2": [78.7121658325],
        "Centroidp1": [0.554832041264],
        "Centroidp2": [0.112445138395],
        "Derivativep1": [715.485229492],
        "Derivativep2": [103.276573181],
        "Meanp1": [-18.932302475],
        "Meanp2": [-3.08703398705],
        "Medianp1": [-19.7944087982],
        "Medianp2": [-3.0517578125e-05],
        "SpKurtp1": [4.91590738297],
        "SpKurtp2": [1.51847743988],
        "SpSkewp1": [2.2407245636],
        "SpSkewp2": [1.45260095596],
        "SpSpreadp1": [0.0419233478606],
        "SpSpreadp2": [0.0488405562937],
        "pointdiffp1": [-8.85439395905],
        "pointdiffp2": [20.2610530853],
        "pointmiddlep1": [2.01894402504],
        "pointmiddlep2": [0.997685015202],
        "pointstartp1": [-6.09927749634],
        "pointstartp2": [-19.9313354492],
        "slopeendp1": [162.777206421],
        "slopeendp2": [51.3829269409],
        "slopeerrorp1": [0.404378324747],
        "slopeerrorp2": [0.0607369877398],
        "slopemiddlep1": [-120.893180847],
        "slopemiddlep2": [29.5869998932],
        "slopestartp1": [-159.56729126],
        "slopestartp2": [154.739501953],
        "stddevp1": [5.21992492676],
        "stddevp2": [4.4040851593]
    },
    "mfcc12": {
        "ARc0p1": [-1.17549435082e-38],
        "ARc0p2": [-1.17549435082e-38],
        "ARc1p1": [-1.17549435082e-38],
        "ARc1p2": [-1.17549435082e-38],
        "ARc2p1": [0.426553606987],
        "ARc2p2": [0.645075082779],
        "ARc3p1": [-1.17549435082e-38],
        "ARc3p2": [-1.17549435082e-38],
        "ARc4p1": [1.4595271349],
        "ARc4p2": [1.32215118408],
        "ARerrp1": [2.11745500565],
        "ARerrp2": [0.513007462025],
        "Accelerationp1": [502.756072998],
        "Accelerationp2": [80.3173370361],
        "Centroidp1": [0.587325572968],
        "Centroidp2": [0.133012205362],
        "Derivativep1": [691.638000488],
        "Derivativep2": [100.026863098],
        "Meanp1": [-13.3594608307],
        "Meanp2": [-0.972587525845],
        "Medianp1": [-10.8030567169],
        "Medianp2": [-3.81469726562e-05],
        "SpKurtp1": [3.59657382965],
        "SpKurtp2": [0.361645936966],
        "SpSkewp1": [1.92526531219],
        "SpSkewp2": [1.04864418507],
        "SpSpreadp1": [0.0453533865511],
        "SpSpreadp2": [0.0539229549468],
        "pointdiffp1": [3.18069767952],
        "pointdiffp2": [6.28713083267],
        "pointmiddlep1": [-0.846863389015],
        "pointmiddlep2": [0.93982064724],
        "pointstartp1": [-12.2723321915],
        "pointstartp2": [-5.95723485947],
        "slopeendp1": [176.847259521],
        "slopeendp2": [80.6954345703],
        "slopeerrorp1": [1.25177741051],
        "slopeerrorp2": [0.180377990007],
        "slopemiddlep1": [-171.812515259],
        "slopemiddlep2": [22.136297226],
        "slopestartp1": [175.518768311],
        "slopestartp2": [154.211044312],
        "stddevp1": [6.02657270432],
        "stddevp2": [1.81174087524]
    },
    "mfcc2": {
        "ARc0p1": [-1.17549435082e-38],
        "ARc0p2": [0.0274309050292],
        "ARc1p1": [0.0395676530898],
        "ARc1p2": [-1.17549435082e-38],
        "ARc2p1": [-1.17549435082e-38],
        "ARc2p2": [0.714768409729],
        "ARc3p1": [-1.17549435082e-38],
        "ARc3p2": [-1.17549435082e-38],
        "ARc4p1": [1.23549509048],
        "ARc4p2": [1.56070005894],
        "ARerrp1": [2.09882736206],
        "ARerrp2": [0.499127805233],
        "Accelerationp1": [990.192993164],
        "Accelerationp2": [84.4541091919],
        "Centroidp1": [0.53923779726],
        "Centroidp2": [0.0144899375737],
        "Derivativep1": [1402.48571777],
        "Derivativep2": [102.833183289],
        "Meanp1": [-72.9996566772],
        "Meanp2": [-4.53591918945],
        "Medianp1": [-74.5664825439],
        "Medianp2": [-6.103515625e-05],
        "SpKurtp1": [0.888194799423],
        "SpKurtp2": [1.60699748993],
        "SpSkewp1": [1.38399243355],
        "SpSkewp2": [1.62964200974],
        "SpSpreadp1": [0.0607323870063],
        "SpSpreadp2": [0.0653399527073],
        "pointdiffp1": [-60.3401145935],
        "pointdiffp2": [71.1863250732],
        "pointmiddlep1": [0.625820100307],
        "pointmiddlep2": [0.920122146606],
        "pointstartp1": [-38.0845947266],
        "pointstartp2": [-60.0413780212],
        "slopeendp1": [-148.15864563],
        "slopeendp2": [136.084274292],
        "slopeerrorp1": [0.152097791433],
        "slopeerrorp2": [0.0887570232153],
        "slopemiddlep1": [53.539264679],
        "slopemiddlep2": [-60.2616920471],
        "slopestartp1": [-155.008728027],
        "slopestartp2": [160.571456909],
        "stddevp1": [9.49181270599],
        "stddevp2": [9.55282592773]
    },
    "mfcc3": {
        "ARc0p1": [1.30828654766],
        "ARc0p2": [-1.17549435082e-38],
        "ARc1p1": [-1.17549435082e-38],
        "ARc1p2": [-1.17549435082e-38],
        "ARc2p1": [0.717686474323],
        "ARc2p2": [0.510048151016],
        "ARc3p1": [-1.17549435082e-38],
        "ARc3p2": [-1.17549435082e-38],
        "ARc4p1": [1.50939142704],
        "ARc4p2": [1.54723072052],
        "ARerrp1": [2.31973934174],
        "ARerrp2": [0.418806165457],
        "Accelerationp1": [749.75201416],
        "Accelerationp2": [70.8878936768],
        "Centroidp1": [0.405183315277],
        "Centroidp2": [0.0768325552344],
        "Derivativep1": [954.157714844],
        "Derivativep2": [81.9841918945],
        "Meanp1": [5.10576152802],
        "Meanp2": [-0.788534939289],
        "Medianp1": [7.33832359314],
        "Medianp2": [8.01086425781e-05],
        "SpKurtp1": [-0.0466554164886],
        "SpKurtp2": [1.32403182983],
        "SpSkewp1": [0.912507414818],
        "SpSkewp2": [1.32728624344],
        "SpSpreadp1": [0.0698123201728],
        "SpSpreadp2": [0.0471163764596],
        "pointdiffp1": [15.0880470276],
        "pointdiffp2": [5.00511646271],
        "pointmiddlep1": [1.96399712563],
        "pointmiddlep2": [1.12148427963],
        "pointstartp1": [-16.2438087463],
        "pointstartp2": [-5.36214256287],
        "slopeendp1": [146.526306152],
        "slopeendp2": [-50.5117340088],
        "slopeerrorp1": [0.20553354919],
        "slopeerrorp2": [0.325399637222],
        "slopemiddlep1": [-144.142105103],
        "slopemiddlep2": [52.4783401489],
        "slopestartp1": [172.391418457],
        "slopestartp2": [154.943664551],
        "stddevp1": [8.5297460556],
        "stddevp2": [2.13668346405]
    },
    "mfcc4": {
        "ARc0p1": [-1.17549435082e-38],
        "ARc0p2": [0.0178501680493],
        "ARc1p1": [0.00188997376245],
        "ARc1p2": [-1.17549435082e-38],
        "ARc2p1": [0.274220317602],
        "ARc2p2": [0.660917818546],
        "ARc3p1": [-1.17549435082e-38],
        "ARc3p2": [-1.17549435082e-38],
        "ARc4p1": [0.136895924807],
        "ARc4p2": [1.46068096161],
        "ARerrp1": [1.14986026287],
        "ARerrp2": [0.366796731949],
        "Accelerationp1": [636.318603516],
        "Accelerationp2": [65.2980041504],
        "Centroidp1": [0.528454065323],
        "Centroidp2": [0.060053858906],
        "Derivativep1": [661.185241699],
        "Derivativep2": [74.708946228],
        "Meanp1": [-50.4905128479],
        "Meanp2": [-6.32461595535],
        "Medianp1": [-52.5838012695],
        "Medianp2": [-6.103515625e-05],
        "SpKurtp1": [1.92325639725],
        "SpKurtp2": [2.47426748276],
        "SpSkewp1": [1.71389818192],
        "SpSkewp2": [1.82880735397],
        "SpSpreadp1": [0.068973518908],
        "SpSpreadp2": [0.0567778460681],
        "pointdiffp1": [-27.441778183],
        "pointdiffp2": [69.4635467529],
        "pointmiddlep1": [1.00653254986],
        "pointmiddlep2": [0.953206062317],
        "pointstartp1": [-28.0820274353],
        "pointstartp2": [-62.0169143677],
        "slopeendp1": [-118.032546997],
        "slopeendp2": [121.891700745],
        "slopeerrorp1": [0.122205197811],
        "slopeerrorp2": [0.0565105564892],
        "slopemiddlep1": [38.1440811157],
        "slopemiddlep2": [-34.0723304749],
        "slopestartp1": [-160.159423828],
        "slopestartp2": [159.114746094],
        "stddevp1": [4.65151262283],
        "stddevp2": [10.5193862915]
    },
    "mfcc5": {
        "ARc0p1": [-1.17549435082e-38],
        "ARc0p2": [0.00356526440009],
        "ARc1p1": [-1.17549435082e-38],
        "ARc1p2": [-1.17549435082e-38],
        "ARc2p1": [0.522884428501],
        "ARc2p2": [0.63614320755],
        "ARc3p1": [-1.17549435082e-38],
        "ARc3p2": [-1.17549435082e-38],
        "ARc4p1": [1.58983230591],
        "ARc4p2": [1.38228547573],
        "ARerrp1": [1.7115483284],
        "ARerrp2": [0.326174736023],
        "Accelerationp1": [826.600891113],
        "Accelerationp2": [57.1592597961],
        "Centroidp1": [0.452537447214],
        "Centroidp2": [0.0673892870545],
        "Derivativep1": [1113.89001465],
        "Derivativep2": [66.6611404419],
        "Meanp1": [-38.2177696228],
        "Meanp2": [-3.99057936668],
        "Medianp1": [-37.1156921387],
        "Medianp2": [2.28881835938e-05],
        "SpKurtp1": [1.33880901337],
        "SpKurtp2": [1.95051622391],
        "SpSkewp1": [1.52287769318],
        "SpSkewp2": [1.68596673012],
        "SpSpreadp1": [0.0525873228908],
        "SpSpreadp2": [0.0572547391057],
        "pointdiffp1": [3.4791829586],
        "pointdiffp2": [40.4044303894],
        "pointmiddlep1": [-2.3936290741],
        "pointmiddlep2": [0.964608192444],
        "pointstartp1": [-33.6651802063],
        "pointstartp2": [-36.6914710999],
        "slopeendp1": [-172.485961914],
        "slopeendp2": [115.79649353],
        "slopeerrorp1": [1.81422269344],
        "slopeerrorp2": [0.0649244189262],
        "slopemiddlep1": [172.321899414],
        "slopemiddlep2": [-25.4942111969],
        "slopestartp1": [-177.015380859],
        "slopestartp2": [158.673583984],
        "stddevp1": [9.83302593231],
        "stddevp2": [6.61510562897]
    },
    "mfcc6": {
        "ARc0p1": [-1.17549435082e-38],
        "ARc0p2": [0.0164140202105],
        "ARc1p1": [-1.17549435082e-38],
        "ARc1p2": [-1.17549435082e-38],
        "ARc2p1": [0.0234437007457],
        "ARc2p2": [0.630124211311],
        "ARc3p1": [-1.17549435082e-38],
        "ARc3p2": [-1.17549435082e-38],
        "ARc4p1": [0.789529204369],
        "ARc4p2": [1.41847920418],
        "ARerrp1": [1.591786623],
        "ARerrp2": [0.404526233673],
        "Accelerationp1": [900.413452148],
        "Accelerationp2": [70.726524353],
        "Centroidp1": [0.50813382864],
        "Centroidp2": [-0.121585696936],
        "Derivativep1": [976.990234375],
        "Derivativep2": [88.6205215454],
        "Meanp1": [-23.0493679047],
        "Meanp2": [-0.234836474061],
        "Medianp1": [-24.2804412842],
        "Medianp2": [-2.67028808594e-05],
        "SpKurtp1": [1.06020736694],
        "SpKurtp2": [0.319101572037],
        "SpSkewp1": [1.39981842041],
        "SpSkewp2": [1.13494646549],
        "SpSpreadp1": [0.0574477352202],
        "SpSpreadp2": [0.0655158385634],
        "pointdiffp1": [-13.754532814],
        "pointdiffp2": [8.51833629608],
        "pointmiddlep1": [1.12051129341],
        "pointmiddlep2": [0.840448856354],
        "pointstartp1": [-10.8378238678],
        "pointstartp2": [-6.42488193512],
        "slopeendp1": [-149.961791992],
        "slopeendp2": [149.181381226],
        "slopeerrorp1": [0.398420780897],
        "slopeerrorp2": [0.228837639093],
        "slopemiddlep1": [116.134986877],
        "slopemiddlep2": [-89.7102661133],
        "slopestartp1": [-166.873458862],
        "slopestartp2": [162.106430054],
        "stddevp1": [5.78271055222],
        "stddevp2": [1.4247033596]
    },
    "mfcc7": {
        "ARc0p1": [-1.17549435082e-38],
        "ARc0p2": [-1.17549435082e-38],
        "ARc1p1": [0.0667650550604],
        "ARc1p2": [-1.17549435082e-38],
        "ARc2p1": [-1.17549435082e-38],
        "ARc2p2": [0.678757071495],
        "ARc3p1": [-1.17549435082e-38],
        "ARc3p2": [-1.17549435082e-38],
        "ARc4p1": [1.02495145798],
        "ARc4p2": [1.45576345921],
        "ARerrp1": [1.53664565086],
        "ARerrp2": [0.462531626225],
        "Accelerationp1": [520.659606934],
        "Accelerationp2": [79.5183181763],
        "Centroidp1": [0.595663428307],
        "Centroidp2": [0.0272378027439],
        "Derivativep1": [800.36315918],
        "Derivativep2": [97.865524292],
        "Meanp1": [-15.5905885696],
        "Meanp2": [-0.457431435585],
        "Medianp1": [-18.0362052917],
        "Medianp2": [-5.34057617188e-05],
        "SpKurtp1": [1.36297988892],
        "SpKurtp2": [0.355980634689],
        "SpSkewp1": [1.47774016857],
        "SpSkewp2": [1.04644703865],
        "SpSpreadp1": [0.059752099216],
        "SpSpreadp2": [0.0548602640629],
        "pointdiffp1": [-21.7622680664],
        "pointdiffp2": [8.40488815308],
        "pointmiddlep1": [1.54471457005],
        "pointmiddlep2": [0.866744220257],
        "pointstartp1": [9.5001449585],
        "pointstartp2": [-6.71218347549],
        "slopeendp1": [113.984634399],
        "slopeendp2": [143.206558228],
        "slopeerrorp1": [0.179473683238],
        "slopeerrorp2": [0.198688313365],
        "slopemiddlep1": [-20.4379882812],
        "slopemiddlep2": [-72.7663116455],
        "slopestartp1": [-163.313201904],
        "slopestartp2": [160.890213013],
        "stddevp1": [6.77918100357],
        "stddevp2": [1.62426352501]
    },
    "mfcc8": {
        "ARc0p1": [-1.17549435082e-38],
        "ARc0p2": [-1.17549435082e-38],
        "ARc1p1": [0.0729340985417],
        "ARc1p2": [-1.17549435082e-38],
        "ARc2p1": [-1.17549435082e-38],
        "ARc2p2": [0.502282500267],
        "ARc3p1": [-1.17549435082e-38],
        "ARc3p2": [-1.17549435082e-38],
        "ARc4p1": [1.25766420364],
        "ARc4p2": [1.48288702965],
        "ARerrp1": [1.26666545868],
        "ARerrp2": [0.521745502949],
        "Accelerationp1": [347.451141357],
        "Accelerationp2": [72.5407028198],
        "Centroidp1": [0.611331224442],
        "Centroidp2": [0.111078448594],
        "Derivativep1": [614.799743652],
        "Derivativep2": [98.9149398804],
        "Meanp1": [-11.490650177],
        "Meanp2": [-1.77295136452],
        "Medianp1": [-14.5753936768],
        "Medianp2": [-4.57763671875e-05],
        "SpKurtp1": [2.00541400909],
        "SpKurtp2": [1.05822181702],
        "SpSkewp1": [1.63970410824],
        "SpSkewp2": [1.26806926727],
        "SpSpreadp1": [0.0537985749543],
        "SpSpreadp2": [0.0490837320685],
        "pointdiffp1": [-20.9253234863],
        "pointdiffp2": [12.1676712036],
        "pointmiddlep1": [1.60436248779],
        "pointmiddlep2": [0.986391365528],
        "pointstartp1": [13.415222168],
        "pointstartp2": [-11.7972288132],
        "slopeendp1": [104.733108521],
        "slopeendp2": [67.5774002075],
        "slopeerrorp1": [0.0994453504682],
        "slopeerrorp2": [0.0787229165435],
        "slopemiddlep1": [6.89588212967],
        "slopemiddlep2": [21.8078899384],
        "slopestartp1": [-164.886962891],
        "slopestartp2": [155.26399231],
        "stddevp1": [7.19442558289],
        "stddevp2": [2.59527635574]
    },
    "mfcc9": {
        "ARc0p1": [-1.17549435082e-38],
        "ARc0p2": [-1.17549435082e-38],
        "ARc1p1": [-1.17549435082e-38],
        "ARc1p2": [-1.17549435082e-38],
        "ARc2p1": [1.00108015537],
        "ARc2p2": [0.577652692795],
        "ARc3p1": [-1.17549435082e-38],
        "ARc3p2": [-1.17549435082e-38],
        "ARc4p1": [1.25897991657],
        "ARc4p2": [1.48251855373],
        "ARerrp1": [1.80960428715],
        "ARerrp2": [0.459923028946],
        "Accelerationp1": [739.926696777],
        "Accelerationp2": [77.9664001465],
        "Centroidp1": [0.511054456234],
        "Centroidp2": [0.10223826766],
        "Derivativep1": [981.547546387],
        "Derivativep2": [87.370803833],
        "Meanp1": [-23.8505077362],
        "Meanp2": [-4.14198255539],
        "Medianp1": [-24.962272644],
        "Medianp2": [-2.28881835938e-05],
        "SpKurtp1": [1.62626981735],
        "SpKurtp2": [1.57106876373],
        "SpSkewp1": [1.59906876087],
        "SpSkewp2": [1.54997098446],
        "SpSpreadp1": [0.0537617616355],
        "SpSpreadp2": [0.0557491257787],
        "pointdiffp1": [-17.6320533752],
        "pointdiffp2": [29.9759120941],
        "pointmiddlep1": [1.16521263123],
        "pointmiddlep2": [0.993576049805],
        "pointstartp1": [-7.70381402969],
        "pointstartp2": [-28.9808330536],
        "slopeendp1": [-147.779602051],
        "slopeendp2": [73.2323074341],
        "slopeerrorp1": [0.327077269554],
        "slopeerrorp2": [0.0497024729848],
        "slopemiddlep1": [114.72946167],
        "slopemiddlep2": [16.0851459503],
        "slopestartp1": [-167.010955811],
        "slopestartp2": [155.936447144],
        "stddevp1": [6.71045827866],
        "stddevp2": [6.00224924088]
    },
    "pitchSalience": {
        "ARc0p1": [0.793584525585],
        "ARc0p2": [0.0343370474875],
        "ARc1p1": [-1.17549435082e-38],
        "ARc1p2": [0.0368231087923],
        "ARc2p1": [0.164586991072],
        "ARc2p2": [0.144328653812],
        "ARc3p1": [-1.17549435082e-38],
        "ARc3p2": [-1.17549435082e-38],
        "ARc4p1": [0.536561310291],
        "ARc4p2": [1.15297579765],
        "ARerrp1": [0.0113070383668],
        "ARerrp2": [0.0355527438223],
        "Accelerationp1": [4.73626661301],
        "Accelerationp2": [5.39763021469],
        "Centroidp1": [0.484694391489],
        "Centroidp2": [0.503197669983],
        "Derivativep1": [6.06252574921],
        "Derivativep2": [6.47108793259],
        "Meanp1": [0.779592037201],
        "Meanp2": [0.616098105907],
        "Medianp1": [0.759566962719],
        "Medianp2": [0.621514678001],
        "SpKurtp1": [0.0635991096497],
        "SpKurtp2": [2.27191305161],
        "SpSkewp1": [1.24494123459],
        "SpSkewp2": [1.76511478424],
        "SpSpreadp1": [0.104461148381],
        "SpSpreadp2": [0.0562642030418],
        "pointdiffp1": [-0.191066816449],
        "pointdiffp2": [-0.0834099203348],
        "pointmiddlep1": [1.19808185101],
        "pointmiddlep2": [2.84730148315],
        "pointstartp1": [0.958488106728],
        "pointstartp2": [0.78816062212],
        "slopeendp1": [-27.283197403],
        "slopeendp2": [125.723846436],
        "slopeerrorp1": [0.161369070411],
        "slopeerrorp2": [0.967911183834],
        "slopemiddlep1": [2.00629377365],
        "slopemiddlep2": [131.485229492],
        "slopestartp1": [-160.525894165],
        "slopestartp2": [-173.198898315],
        "stddevp1": [0.0572984851897],
        "stddevp2": [0.0984666123986]
    },
    "pitchYin-st": {
        "ARc0p1": [1046.91625977],
        "ARc0p2": [54.5634498596],
        "ARc1p1": [-1.17549435082e-38],
        "ARc1p2": [0.15064021945],
        "ARc2p1": [0.37636756897],
        "ARc2p2": [0.164126053452],
        "ARc3p1": [-1.17549435082e-38],
        "ARc3p2": [-1.17549435082e-38],
        "ARc4p1": [0.6151278615],
        "ARc4p2": [0.657442331314],
        "ARerrp1": [518.743896484],
        "ARerrp2": [239.084442139],
        "Accelerationp1": [105.568397522],
        "Accelerationp2": [88.8955230713],
        "Centroidp1": [-48.9189071655],
        "Centroidp2": [-44.2302207947],
        "Derivativep1": [97.9976348877],
        "Derivativep2": [84.5007171631],
        "Meanp1": [40.909778595],
        "Meanp2": [49.6663093567],
        "Medianp1": [32.7910881042],
        "Medianp2": [41.2650032043],
        "SpKurtp1": [-0.744961023331],
        "SpKurtp2": [-0.366947174072],
        "SpSkewp1": [0.555027782917],
        "SpSkewp2": [0.940327644348],
        "SpSpreadp1": [0.0740740150213],
        "SpSpreadp2": [0.0854336619377],
        "pointdiffp1": [-540.412658691],
        "pointdiffp2": [457.543304443],
        "pointmiddlep1": [-0.902593195438],
        "pointmiddlep2": [-0.524810433388],
        "pointstartp1": [647.053344727],
        "pointstartp2": [1847.94250488],
        "slopeendp1": [-168.987976074],
        "slopeendp2": [-176.942108154],
        "slopeerrorp1": [1.39814019203],
        "slopeerrorp2": [1.43378341198],
        "slopemiddlep1": [82.7919158936],
        "slopemiddlep2": [174.860397339],
        "slopestartp1": [80.5559539795],
        "slopestartp2": [-177.491165161],
        "stddevp1": [40.3182868958],
        "stddevp2": [49.3326454163]
    },
    "pitchYinConfidence": {
        "ARc0p1": [0.0605622380972],
        "ARc0p2": [0.0153870945796],
        "ARc1p1": [0.123797081411],
        "ARc1p2": [0.106470398605],
        "ARc2p1": [0.538558959961],
        "ARc2p2": [0.0924809128046],
        "ARc3p1": [-1.17549435082e-38],
        "ARc3p2": [-1.17549435082e-38],
        "ARc4p1": [0.242553412914],
        "ARc4p2": [1.21302831173],
        "ARerrp1": [0.00945534650236],
        "ARerrp2": [0.0365895330906],
        "Accelerationp1": [4.67838954926],
        "Accelerationp2": [5.46919870377],
        "Centroidp1": [0.442510992289],
        "Centroidp2": [0.567927479744],
        "Derivativep1": [4.93144655228],
        "Derivativep2": [6.78633785248],
        "Meanp1": [0.236173018813],
        "Meanp2": [0.487716734409],
        "Medianp1": [0.220517039299],
        "Medianp2": [0.483213305473],
        "SpKurtp1": [-0.106721639633],
        "SpKurtp2": [2.63154792786],
        "SpSkewp1": [1.16221249104],
        "SpSkewp2": [1.81712245941],
        "SpSpreadp1": [0.103519752622],
        "SpSpreadp2": [0.0516340248287],
        "pointdiffp1": [-0.166670784354],
        "pointdiffp2": [-0.0130879757926],
        "pointmiddlep1": [0.870480418205],
        "pointmiddlep2": [-2.30036425591],
        "pointstartp1": [0.358101069927],
        "pointstartp2": [0.469857990742],
        "slopeendp1": [-35.1764831543],
        "slopeendp2": [-179.323852539],
        "slopeerrorp1": [0.110551461577],
        "slopeerrorp2": [5.96550178528],
        "slopemiddlep1": [-61.9735565186],
        "slopemiddlep2": [178.523086548],
        "slopestartp1": [-146.098098755],
        "slopestartp2": [-179.220626831],
        "stddevp1": [0.0428531989455],
        "stddevp2": [0.150965377688]
    },
    "spectral_crest": {
        "ARc0p1": [1.35998547077],
        "ARc0p2": [0.301880329847],
        "ARc1p1": [0.027561744675],
        "ARc1p2": [-1.17549435082e-38],
        "ARc2p1": [-1.17549435082e-38],
        "ARc2p2": [0.416359007359],
        "ARc3p1": [0.093794606626],
        "ARc3p2": [-1.17549435082e-38],
        "ARc4p1": [0.690307557583],
        "ARc4p2": [1.78843092918],
        "ARerrp1": [0.31556391716],
        "ARerrp2": [0.540427982807],
        "Accelerationp1": [77.1215744019],
        "Accelerationp2": [81.1088790894],
        "Centroidp1": [0.446121245623],
        "Centroidp2": [0.571656227112],
        "Derivativep1": [73.5766525269],
        "Derivativep2": [123.577262878],
        "Meanp1": [5.0799202919],
        "Meanp2": [18.3981304169],
        "Medianp1": [4.66238451004],
        "Medianp2": [20.8882312775],
        "SpKurtp1": [0.378801822662],
        "SpKurtp2": [7.51232242584],
        "SpSkewp1": [1.32573902607],
        "SpSkewp2": [2.66254091263],
        "SpSpreadp1": [0.0949611067772],
        "SpSpreadp2": [0.0314582251012],
        "pointdiffp1": [-3.87459540367],
        "pointdiffp2": [-0.00158712873235],
        "pointmiddlep1": [0.781077325344],
        "pointmiddlep2": [-6217.97607422],
        "pointstartp1": [7.69788074493],
        "pointstartp2": [11.8277196884],
        "slopeendp1": [-108.07359314],
        "slopeendp2": [-179.999191284],
        "slopeerrorp1": [0.0916655138135],
        "slopeerrorp2": [1453.33374023],
        "slopemiddlep1": [-27.9355354309],
        "slopemiddlep2": [179.996139526],
        "slopestartp1": [-149.171264648],
        "slopestartp2": [-179.996154785],
        "stddevp1": [0.920405507088],
        "stddevp2": [6.35041046143]
    },
    "spectral_flatness_db": {
        "ARc0p1": [0.0186306256801],
        "ARc0p2": [0.00598827563226],
        "ARc1p1": [-1.17549435082e-38],
        "ARc1p2": [-1.17549435082e-38],
        "ARc2p1": [1.16629481316],
        "ARc2p2": [0.512307524681],
        "ARc3p1": [-1.17549435082e-38],
        "ARc3p2": [-1.17549435082e-38],
        "ARc4p1": [1.70157146454],
        "ARc4p2": [1.72650957108],
        "ARerrp1": [0.00163699372206],
        "ARerrp2": [0.0060607669875],
        "Accelerationp1": [0.686792194843],
        "Accelerationp2": [0.882908463478],
        "Centroidp1": [0.453211456537],
        "Centroidp2": [0.564892649651],
        "Derivativep1": [0.86557084322],
        "Derivativep2": [1.37321400642],
        "Meanp1": [0.0876885354519],
        "Meanp2": [0.179007768631],
        "Medianp1": [0.0806697979569],
        "Medianp2": [0.189547017217],
        "SpKurtp1": [0.792010307312],
        "SpKurtp2": [4.58986663818],
        "SpSkewp1": [1.45065891743],
        "SpSkewp2": [2.15134501457],
        "SpSpreadp1": [0.0881881862879],
        "SpSpreadp2": [0.0379758216441],
        "pointdiffp1": [-0.0386038459837],
        "pointdiffp2": [0.0202813930809],
        "pointmiddlep1": [0.891933560371],
        "pointmiddlep2": [4.68698501587],
        "pointstartp1": [0.116446793079],
        "pointstartp2": [0.112327985466],
        "slopeendp1": [108.237472534],
        "slopeendp2": [-177.462463379],
        "slopeerrorp1": [0.16941139102],
        "slopeerrorp2": [1.09355592728],
        "slopemiddlep1": [-109.207725525],
        "slopemiddlep2": [172.70954895],
        "slopestartp1": [-120.59752655],
        "slopestartp2": [-170.182418823],
        "stddevp1": [0.0148315187544],
        "stddevp2": [0.0569386146963]
    },
    "tristimulus0": {
        "ARc0p1": [0.000797325570602],
        "ARc0p2": [0.0150305461138],
        "ARc1p1": [-1.17549435082e-38],
        "ARc1p2": [-1.17549435082e-38],
        "ARc2p1": [-1.17549435082e-38],
        "ARc2p2": [0.100382186472],
        "ARc3p1": [0.523041248322],
        "ARc3p2": [0.187991201878],
        "ARc4p1": [0.0300987511873],
        "ARc4p2": [0.490597426891],
        "ARerrp1": [0.00841786153615],
        "ARerrp2": [0.049471128732],
        "Accelerationp1": [3.17917346954],
        "Accelerationp2": [8.4612531662],
        "Centroidp1": [0.23726169765],
        "Centroidp2": [0.610621809959],
        "Derivativep1": [3.02274656296],
        "Derivativep2": [8.77860927582],
        "Meanp1": [0.0165470503271],
        "Meanp2": [0.0514578707516],
        "Medianp1": [0.00078202446457],
        "Medianp2": [0.0155934933573],
        "SpKurtp1": [-1.19483852386],
        "SpKurtp2": [-0.998479127884],
        "SpSkewp1": [0.535330712795],
        "SpSkewp2": [0.614713549614],
        "SpSpreadp1": [0.12575545907],
        "SpSpreadp2": [0.093477204442],
        "pointdiffp1": [0.00388497579843],
        "pointdiffp2": [0.208876281977],
        "pointmiddlep1": [2.13033676147],
        "pointmiddlep2": [0.396357804537],
        "pointstartp1": [0.0106459213421],
        "pointstartp2": [-0.0385665670037],
        "slopeendp1": [178.438156128],
        "slopeendp2": [156.448303223],
        "slopeerrorp1": [4.44205617905],
        "slopeerrorp2": [0.263718694448],
        "slopemiddlep1": [-177.019256592],
        "slopemiddlep2": [-69.2942810059],
        "slopestartp1": [178.674087524],
        "slopestartp2": [151.707778931],
        "stddevp1": [0.0241910032928],
        "stddevp2": [0.0540029667318]
    },
    "tristimulus1": {
        "ARc0p1": [0.0408001951873],
        "ARc0p2": [0.0345127619803],
        "ARc1p1": [-1.17549435082e-38],
        "ARc1p2": [0.0980612039566],
        "ARc2p1": [0.626702487469],
        "ARc2p2": [0.194924414158],
        "ARc3p1": [-1.17549435082e-38],
        "ARc3p2": [0.253470391035],
        "ARc4p1": [0.536432147026],
        "ARc4p2": [0.251649320126],
        "ARerrp1": [0.0117541430518],
        "ARerrp2": [0.0467215590179],
        "Accelerationp1": [6.19905328751],
        "Accelerationp2": [7.50464677811],
        "Centroidp1": [0.35657030344],
        "Centroidp2": [0.489954084158],
        "Derivativep1": [7.74132823944],
        "Derivativep2": [8.55987739563],
        "Meanp1": [0.128311231732],
        "Meanp2": [0.171383589506],
        "Medianp1": [0.104855015874],
        "Medianp2": [0.158983811736],
        "SpKurtp1": [1.09529447556],
        "SpKurtp2": [-1.2724301815],
        "SpSkewp1": [1.36243379116],
        "SpSkewp2": [0.395247399807],
        "SpSpreadp1": [0.0613393783569],
        "SpSpreadp2": [0.108061954379],
        "pointdiffp1": [-0.159983754158],
        "pointdiffp2": [-0.00320507958531],
        "pointmiddlep1": [0.625068485737],
        "pointmiddlep2": [-57.9841117859],
        "pointstartp1": [0.220808684826],
        "pointstartp2": [0.0481829605997],
        "slopeendp1": [82.9602432251],
        "slopeendp2": [-179.448974609],
        "slopeerrorp1": [0.243221849203],
        "slopeerrorp2": [14.9839401245],
        "slopemiddlep1": [-118.830329895],
        "slopemiddlep2": [-172.178070068],
        "slopestartp1": [-13.2840471268],
        "slopestartp2": [179.560302734],
        "stddevp1": [0.0629768967628],
        "stddevp2": [0.0687127932906]
    },
    "tristimulus2": {
        "ARc0p1": [0.461625248194],
        "ARc0p2": [0.0358801148832],
        "ARc1p1": [-1.17549435082e-38],
        "ARc1p2": [0.00574213126674],
        "ARc2p1": [0.299079239368],
        "ARc2p2": [0.20044721663],
        "ARc3p1": [0.0720446184278],
        "ARc3p2": [-1.17549435082e-38],
        "ARc4p1": [0.209511071444],
        "ARc4p2": [0.900771200657],
        "ARerrp1": [0.0211539529264],
        "ARerrp2": [0.0319453589618],
        "Accelerationp1": [8.15420150757],
        "Accelerationp2": [4.79924249649],
        "Centroidp1": [0.526605129242],
        "Centroidp2": [0.485980272293],
        "Derivativep1": [8.67053318024],
        "Derivativep2": [5.40785312653],
        "Meanp1": [0.855141818523],
        "Meanp2": [0.76341509819],
        "Medianp1": [0.895011901855],
        "Medianp2": [0.78340369463],
        "SpKurtp1": [0.139271736145],
        "SpKurtp2": [1.72098302841],
        "SpSkewp1": [1.30230998993],
        "SpSkewp2": [1.66520833969],
        "SpSpreadp1": [0.105898022652],
        "SpSpreadp2": [0.0627672001719],
        "pointdiffp1": [0.156098693609],
        "pointdiffp2": [-0.454757004976],
        "pointmiddlep1": [0.58760613203],
        "pointmiddlep2": [0.652551651001],
        "pointstartp1": [0.768545389175],
        "pointstartp2": [1.03698384762],
        "slopeendp1": [-139.780807495],
        "slopeendp2": [-151.895767212],
        "slopeerrorp1": [0.308168441057],
        "slopeerrorp2": [0.161842629313],
        "slopemiddlep1": [139.220794678],
        "slopemiddlep2": [77.5087051392],
        "slopestartp1": [-127.556968689],
        "slopestartp2": [-158.293228149],
        "stddevp1": [0.0813135579228],
        "stddevp2": [0.0852360501885]
    }
},
"slice": {
    "time": [[0, 4.61167812347]]
},
"Class": {
    "type0": "Snare",
    "type1": "timbre",
    "type2": "rAyotte",
    "type3": "Sd",
    "type4": "none"
},
"audiopath": "\/Users\/mhermant\/Documents\/Work\/Datasets\/DrumKitFromHell\/Snare.timbre.rAyotte Sd H05  x.wav"
}