{
"metadata": {
    "version": {
        "essentia": "2.1-beta2"
    }
},
"values": {
    "barkbands_kurtosis": {
        "ARc0p1": [0.811841607094],
        "ARc0p2": [10.6215019226],
        "ARc1p1": [-1.17549435082e-38],
        "ARc1p2": [-1.17549435082e-38],
        "ARc2p1": [0.973817050457],
        "ARc2p2": [0.462047636509],
        "ARc3p1": [-1.17549435082e-38],
        "ARc3p2": [-1.17549435082e-38],
        "ARc4p1": [1.85142445564],
        "ARc4p2": [1.12710869312],
        "ARerrp1": [0.619931995869],
        "ARerrp2": [6.45928525925],
        "Accelerationp1": [295.307952881],
        "Accelerationp2": [902.160339355],
        "Centroidp1": [0.310614854097],
        "Centroidp2": [0.490240633488],
        "Derivativep1": [506.975341797],
        "Derivativep2": [1017.60723877],
        "Meanp1": [9.8251657486],
        "Meanp2": [28.8892478943],
        "Medianp1": [4.93255567551],
        "Medianp2": [26.5128383636],
        "SpKurtp1": [4.20244693756],
        "SpKurtp2": [-0.217110157013],
        "SpSkewp1": [2.10339426994],
        "SpSkewp2": [0.776394963264],
        "SpSpreadp1": [0.0500467717648],
        "SpSpreadp2": [0.0576404519379],
        "pointdiffp1": [-6.10708904266],
        "pointdiffp2": [4.83505678177],
        "pointmiddlep1": [0.308177441359],
        "pointmiddlep2": [3.24142098427],
        "pointstartp1": [12.1465377808],
        "pointstartp2": [17.6456165314],
        "slopeendp1": [170.431213379],
        "slopeendp2": [-110.626686096],
        "slopeerrorp1": [0.568397760391],
        "slopeerrorp2": [2.66487431526],
        "slopemiddlep1": [-165.494140625],
        "slopemiddlep2": [-145.897842407],
        "slopestartp1": [171.516265869],
        "slopestartp2": [174.411621094],
        "stddevp1": [6.92485189438],
        "stddevp2": [14.1598129272]
    },
    "barkbands_skewness": {
        "ARc0p1": [0.299514740705],
        "ARc0p2": [0.351299792528],
        "ARc1p1": [-1.17549435082e-38],
        "ARc1p2": [-1.17549435082e-38],
        "ARc2p1": [1.41039097309],
        "ARc2p2": [0.677741527557],
        "ARc3p1": [-1.17549435082e-38],
        "ARc3p2": [-1.17549435082e-38],
        "ARc4p1": [2.06668186188],
        "ARc4p2": [1.65532279015],
        "ARerrp1": [0.0764534324408],
        "ARerrp2": [0.314908593893],
        "Accelerationp1": [34.5913162231],
        "Accelerationp2": [52.3040122986],
        "Centroidp1": [0.398951292038],
        "Centroidp2": [0.520102739334],
        "Derivativep1": [61.0707092285],
        "Derivativep2": [71.5416030884],
        "Meanp1": [2.64507126808],
        "Meanp2": [4.16725540161],
        "Medianp1": [2.25980162621],
        "Medianp2": [4.42006778717],
        "SpKurtp1": [2.11626577377],
        "SpKurtp2": [1.67382764816],
        "SpSkewp1": [1.81871414185],
        "SpSkewp2": [1.4550344944],
        "SpSpreadp1": [0.0751586183906],
        "SpSpreadp2": [0.0427831560373],
        "pointdiffp1": [-1.15371131897],
        "pointdiffp2": [-1.69140076637],
        "pointmiddlep1": [0.258321940899],
        "pointmiddlep2": [-2.04801702499],
        "pointstartp1": [3.04766011238],
        "pointstartp2": [2.14323067665],
        "slopeendp1": [163.741210938],
        "slopeendp2": [-174.033187866],
        "slopeerrorp1": [0.293284595013],
        "slopeerrorp2": [0.607198119164],
        "slopemiddlep1": [-159.330352783],
        "slopemiddlep2": [143.0912323],
        "slopestartp1": [167.227035522],
        "slopestartp2": [100.339630127],
        "stddevp1": [0.923808932304],
        "stddevp2": [1.68242263794]
    },
    "barkbands_spread": {
        "ARc0p1": [0.967218279839],
        "ARc0p2": [0.644371926785],
        "ARc1p1": [-1.17549435082e-38],
        "ARc1p2": [0.077643930912],
        "ARc2p1": [1.26484394073],
        "ARc2p2": [0.230532750487],
        "ARc3p1": [-1.17549435082e-38],
        "ARc3p2": [-1.17549435082e-38],
        "ARc4p1": [2.23283720016],
        "ARc4p2": [1.72260272503],
        "ARerrp1": [0.381800174713],
        "ARerrp2": [1.69567883015],
        "Accelerationp1": [123.548286438],
        "Accelerationp2": [275.179840088],
        "Centroidp1": [0.623856008053],
        "Centroidp2": [0.708526492119],
        "Derivativep1": [184.619430542],
        "Derivativep2": [396.132568359],
        "Meanp1": [7.28641271591],
        "Meanp2": [15.5486526489],
        "Medianp1": [7.95145988464],
        "Medianp2": [10.0577163696],
        "SpKurtp1": [0.55543088913],
        "SpKurtp2": [4.05158567429],
        "SpSkewp1": [1.3391700983],
        "SpSkewp2": [1.95637190342],
        "SpSpreadp1": [0.087920345366],
        "SpSpreadp2": [0.0392274968326],
        "pointdiffp1": [8.00469398499],
        "pointdiffp2": [51.7897605896],
        "pointmiddlep1": [0.340376317501],
        "pointmiddlep2": [0.134449765086],
        "pointstartp1": [4.08265209198],
        "pointstartp2": [2.25993347168],
        "slopeendp1": [43.9683761597],
        "slopeendp2": [149.902252197],
        "slopeerrorp1": [0.143387064338],
        "slopeerrorp2": [0.122086361051],
        "slopemiddlep1": [116.545280457],
        "slopemiddlep2": [40.7562828064],
        "slopestartp1": [-82.2607727051],
        "slopestartp2": [76.9610824585],
        "stddevp1": [2.90345239639],
        "stddevp2": [10.6822214127]
    },
    "envelope": {
        "ARc0p1": [9.78133769536e-08],
        "ARc0p2": [-1.17549435082e-38],
        "ARc1p1": [-1.17549435082e-38],
        "ARc1p2": [0.0891248136759],
        "ARc2p1": [2.12368583679],
        "ARc2p2": [0.279139459133],
        "ARc3p1": [-1.17549435082e-38],
        "ARc3p2": [-1.17549435082e-38],
        "ARc4p1": [3.26253008842],
        "ARc4p2": [2.44140958786],
        "ARerrp1": [2.28084203968e-07],
        "ARerrp2": [2.98468250115e-10],
        "Accelerationp1": [0.0231741592288],
        "Accelerationp2": [1.05052131403e-05],
        "Centroidp1": [0.593460559845],
        "Centroidp2": [0.268346637487],
        "Derivativep1": [0.326367616653],
        "Derivativep2": [0.00597303221002],
        "Meanp1": [0.0250025819987],
        "Meanp2": [0.00911469664425],
        "Medianp1": [0.0307793486863],
        "Medianp2": [0.00609163334593],
        "SpKurtp1": [8.06087112427],
        "SpKurtp2": [7.95727920532],
        "SpSkewp1": [2.9198615551],
        "SpSkewp2": [2.90374755859],
        "SpSpreadp1": [0.03707671538],
        "SpSpreadp2": [0.037325322628],
        "pointdiffp1": [0.0417635142803],
        "pointdiffp2": [-0.0292124561965],
        "pointmiddlep1": [1.02381551266],
        "pointmiddlep2": [0.825994610786],
        "pointstartp1": [-0.0104601169005],
        "pointstartp2": [0.0300697609782],
        "slopeendp1": [57.6441116333],
        "slopeendp2": [-39.5409660339],
        "slopeerrorp1": [0.0480310283601],
        "slopeerrorp2": [0.00393224041909],
        "slopemiddlep1": [20.1017799377],
        "slopemiddlep2": [-67.5092010498],
        "slopestartp1": [156.178375244],
        "slopestartp2": [-142.753372192],
        "stddevp1": [0.00878544896841],
        "stddevp2": [0.00649625342339]
    },
    "mfcc0": {
        "ARc0p1": [-1.17549435082e-38],
        "ARc0p2": [-1.17549435082e-38],
        "ARc1p1": [0.00881976447999],
        "ARc1p2": [-1.17549435082e-38],
        "ARc2p1": [-1.17549435082e-38],
        "ARc2p2": [0.952834486961],
        "ARc3p1": [-1.17549435082e-38],
        "ARc3p2": [-1.17549435082e-38],
        "ARc4p1": [1.26303815842],
        "ARc4p2": [1.73311543465],
        "ARerrp1": [2.09704327583],
        "ARerrp2": [0.248037546873],
        "Accelerationp1": [1765.31604004],
        "Accelerationp2": [43.4642982483],
        "Centroidp1": [0.502951025963],
        "Centroidp2": [0.501442670822],
        "Derivativep1": [3466.33837891],
        "Derivativep2": [62.8546447754],
        "Meanp1": [-952.924865723],
        "Meanp2": [-1134.81982422],
        "Medianp1": [-951.237304688],
        "Medianp2": [-1138.42004395],
        "SpKurtp1": [0.0472433567047],
        "SpKurtp2": [45.0807609558],
        "SpSkewp1": [1.2552895546],
        "SpSkewp2": [6.47232103348],
        "SpSpreadp1": [0.106747880578],
        "SpSpreadp2": [0.0103061432019],
        "pointdiffp1": [71.8088150024],
        "pointdiffp2": [-49.2077941895],
        "pointmiddlep1": [2.00122761726],
        "pointmiddlep2": [0.914826989174],
        "pointstartp1": [-1056.2052002],
        "pointstartp2": [-1096.61938477],
        "slopeendp1": [149.248138428],
        "slopeendp2": [-134.027114868],
        "slopeerrorp1": [0.234508737922],
        "slopeerrorp2": [0.0934793278575],
        "slopemiddlep1": [-146.481567383],
        "slopemiddlep2": [53.8923149109],
        "slopestartp1": [172.686721802],
        "slopestartp2": [-160.016891479],
        "stddevp1": [38.6801834106],
        "stddevp2": [5.7167801857]
    },
    "mfcc1": {
        "ARc0p1": [10.7281389236],
        "ARc0p2": [0.0266438443214],
        "ARc1p1": [0.0244120266289],
        "ARc1p2": [-1.17549435082e-38],
        "ARc2p1": [-1.17549435082e-38],
        "ARc2p2": [0.891845464706],
        "ARc3p1": [-1.17549435082e-38],
        "ARc3p2": [-1.17549435082e-38],
        "ARc4p1": [1.33229374886],
        "ARc4p2": [1.68490731716],
        "ARerrp1": [2.58947038651],
        "ARerrp2": [0.289074778557],
        "Accelerationp1": [1160.76147461],
        "Accelerationp2": [51.4610176086],
        "Centroidp1": [0.475728780031],
        "Centroidp2": [0.053894970566],
        "Derivativep1": [1877.07104492],
        "Derivativep2": [70.5864868164],
        "Meanp1": [111.919944763],
        "Meanp2": [3.94312357903],
        "Medianp1": [111.592918396],
        "Medianp2": [1.14440917969e-05],
        "SpKurtp1": [3.02261638641],
        "SpKurtp2": [1.04193210602],
        "SpSkewp1": [1.94764637947],
        "SpSkewp2": [1.45116758347],
        "SpSpreadp1": [0.059138763696],
        "SpSpreadp2": [0.0668576210737],
        "pointdiffp1": [16.5513839722],
        "pointdiffp2": [-49.4912719727],
        "pointmiddlep1": [2.82680821419],
        "pointmiddlep2": [0.9245454669],
        "pointstartp1": [79.5743103027],
        "pointstartp2": [42.6796455383],
        "slopeendp1": [166.515762329],
        "slopeendp2": [-130.808624268],
        "slopeerrorp1": [0.744494318962],
        "slopeerrorp2": [0.0800281986594],
        "slopemiddlep1": [-164.573272705],
        "slopemiddlep2": [47.632522583],
        "slopestartp1": [175.769943237],
        "slopestartp2": [-159.683654785],
        "stddevp1": [17.6932582855],
        "stddevp2": [6.17426347733]
    },
    "mfcc10": {
        "ARc0p1": [-1.17549435082e-38],
        "ARc0p2": [-1.17549435082e-38],
        "ARc1p1": [-1.17549435082e-38],
        "ARc1p2": [-1.17549435082e-38],
        "ARc2p1": [0.889907598495],
        "ARc2p2": [0.906136512756],
        "ARc3p1": [-1.17549435082e-38],
        "ARc3p2": [-1.17549435082e-38],
        "ARc4p1": [1.47370874882],
        "ARc4p2": [1.6524181366],
        "ARerrp1": [0.826526761055],
        "ARerrp2": [0.246800407767],
        "Accelerationp1": [403.942779541],
        "Accelerationp2": [42.5798110962],
        "Centroidp1": [0.507259607315],
        "Centroidp2": [0.0727104619145],
        "Derivativep1": [500.121612549],
        "Derivativep2": [56.0418243408],
        "Meanp1": [-22.4320373535],
        "Meanp2": [-2.34070754051],
        "Medianp1": [-22.8060665131],
        "Medianp2": [-2.67028808594e-05],
        "SpKurtp1": [2.83353376389],
        "SpKurtp2": [1.56044864655],
        "SpSkewp1": [1.88725292683],
        "SpSkewp2": [1.5519361496],
        "SpSpreadp1": [0.0582436993718],
        "SpSpreadp2": [0.0600888505578],
        "pointdiffp1": [-16.5987453461],
        "pointdiffp2": [24.1494541168],
        "pointmiddlep1": [1.32637858391],
        "pointmiddlep2": [0.948140501976],
        "pointstartp1": [-5.55963468552],
        "pointstartp2": [-21.6217784882],
        "slopeendp1": [-144.795043945],
        "slopeendp2": [120.153511047],
        "slopeerrorp1": [0.101284593344],
        "slopeerrorp2": [0.0591316856444],
        "slopemiddlep1": [119.90411377],
        "slopemiddlep2": [-29.6826858521],
        "slopestartp1": [-168.304016113],
        "slopestartp2": [158.719192505],
        "stddevp1": [4.63516950607],
        "stddevp2": [3.57797288895]
    },
    "mfcc11": {
        "ARc0p1": [-1.17549435082e-38],
        "ARc0p2": [-1.17549435082e-38],
        "ARc1p1": [0.104782640934],
        "ARc1p2": [-1.17549435082e-38],
        "ARc2p1": [0.217153772712],
        "ARc2p2": [0.783484756947],
        "ARc3p1": [-1.17549435082e-38],
        "ARc3p2": [-1.17549435082e-38],
        "ARc4p1": [1.04217839241],
        "ARc4p2": [1.67514932156],
        "ARerrp1": [1.66182363033],
        "ARerrp2": [0.252022773027],
        "Accelerationp1": [535.832397461],
        "Accelerationp2": [47.6971092224],
        "Centroidp1": [0.556669592857],
        "Centroidp2": [0.0704600512981],
        "Derivativep1": [654.000549316],
        "Derivativep2": [60.3621292114],
        "Meanp1": [-24.0275745392],
        "Meanp2": [-2.54801535606],
        "Medianp1": [-25.2398452759],
        "Medianp2": [-3.0517578125e-05],
        "SpKurtp1": [2.42715072632],
        "SpKurtp2": [1.96021413803],
        "SpSkewp1": [1.8646171093],
        "SpSkewp2": [1.63637113571],
        "SpSpreadp1": [0.0677961334586],
        "SpSpreadp2": [0.0566860288382],
        "pointdiffp1": [-15.7452640533],
        "pointdiffp2": [27.0547142029],
        "pointmiddlep1": [1.42824721336],
        "pointmiddlep2": [0.943820297718],
        "pointstartp1": [-7.02025842667],
        "pointstartp2": [-24.0708312988],
        "slopeendp1": [131.89050293],
        "slopeendp2": [122.225509644],
        "slopeerrorp1": [0.15183211863],
        "slopeerrorp2": [0.0609536245465],
        "slopemiddlep1": [-74.7330474854],
        "slopemiddlep2": [-32.7516136169],
        "slopestartp1": [-158.171127319],
        "slopestartp2": [158.876144409],
        "stddevp1": [5.82087039948],
        "stddevp2": [3.89707612991]
    },
    "mfcc12": {
        "ARc0p1": [-1.17549435082e-38],
        "ARc0p2": [-1.17549435082e-38],
        "ARc1p1": [-1.17549435082e-38],
        "ARc1p2": [-1.17549435082e-38],
        "ARc2p1": [0.74881285429],
        "ARc2p2": [0.752908825874],
        "ARc3p1": [-1.17549435082e-38],
        "ARc3p2": [-1.17549435082e-38],
        "ARc4p1": [1.317019701],
        "ARc4p2": [1.61663746834],
        "ARerrp1": [1.66578269005],
        "ARerrp2": [0.247400715947],
        "Accelerationp1": [384.33682251],
        "Accelerationp2": [42.3939704895],
        "Centroidp1": [0.523715853691],
        "Centroidp2": [0.0744938850403],
        "Derivativep1": [570.11895752],
        "Derivativep2": [57.9756965637],
        "Meanp1": [-30.1701412201],
        "Meanp2": [-2.26567935944],
        "Medianp1": [-30.0445976257],
        "Medianp2": [-3.81469726562e-05],
        "SpKurtp1": [2.78996324539],
        "SpKurtp2": [1.65474224091],
        "SpSkewp1": [1.96014130116],
        "SpSkewp2": [1.58091211319],
        "SpSpreadp1": [0.0658749639988],
        "SpSpreadp2": [0.0580758489668],
        "pointdiffp1": [-3.96572804451],
        "pointdiffp2": [23.1079940796],
        "pointmiddlep1": [4.62807226181],
        "pointmiddlep2": [0.94799888134],
        "pointstartp1": [-17.9555225372],
        "pointstartp2": [-20.7130661011],
        "slopeendp1": [174.586029053],
        "slopeendp2": [119.643997192],
        "slopeerrorp1": [0.475232213736],
        "slopeerrorp2": [0.0590347014368],
        "slopemiddlep1": [-150.643218994],
        "slopemiddlep2": [-28.7009716034],
        "slopestartp1": [-170.375335693],
        "slopestartp2": [158.645233154],
        "stddevp1": [5.32619094849],
        "stddevp2": [3.446352005]
    },
    "mfcc2": {
        "ARc0p1": [-1.17549435082e-38],
        "ARc0p2": [0.0477127097547],
        "ARc1p1": [-1.17549435082e-38],
        "ARc1p2": [-1.17549435082e-38],
        "ARc2p1": [0.851385116577],
        "ARc2p2": [1.05948829651],
        "ARc3p1": [-1.17549435082e-38],
        "ARc3p2": [-1.17549435082e-38],
        "ARc4p1": [1.83299636841],
        "ARc4p2": [1.90816950798],
        "ARerrp1": [1.73038947582],
        "ARerrp2": [0.284155994654],
        "Accelerationp1": [617.051452637],
        "Accelerationp2": [44.5934753418],
        "Centroidp1": [0.58267724514],
        "Centroidp2": [0.0831914916635],
        "Derivativep1": [1071.85900879],
        "Derivativep2": [62.2297363281],
        "Meanp1": [-25.8406963348],
        "Meanp2": [2.04024291039],
        "Medianp1": [-27.0918235779],
        "Medianp2": [-6.103515625e-05],
        "SpKurtp1": [2.51171159744],
        "SpKurtp2": [3.39680767059],
        "SpSkewp1": [1.69636273384],
        "SpSkewp2": [2.00191307068],
        "SpSpreadp1": [0.0491647683084],
        "SpSpreadp2": [0.0480219945312],
        "pointdiffp1": [-42.6274032593],
        "pointdiffp2": [-18.1870307922],
        "pointmiddlep1": [1.30441021919],
        "pointmiddlep2": [0.97218132019],
        "pointstartp1": [16.9042072296],
        "pointstartp2": [16.8519573212],
        "slopeendp1": [-63.5214881897],
        "slopeendp2": [-105.723495483],
        "slopeerrorp1": [0.0862239152193],
        "slopeerrorp2": [0.0851641073823],
        "slopemiddlep1": [45.4049034119],
        "slopemiddlep2": [11.9382410049],
        "slopestartp1": [-163.864089966],
        "slopestartp2": [-157.804031372],
        "stddevp1": [9.88924789429],
        "stddevp2": [3.35877275467]
    },
    "mfcc3": {
        "ARc0p1": [-1.17549435082e-38],
        "ARc0p2": [0.0618274323642],
        "ARc1p1": [-1.17549435082e-38],
        "ARc1p2": [-1.17549435082e-38],
        "ARc2p1": [0.52441829443],
        "ARc2p2": [0.76757389307],
        "ARc3p1": [-1.17549435082e-38],
        "ARc3p2": [-1.17549435082e-38],
        "ARc4p1": [1.66907083988],
        "ARc4p2": [1.73551487923],
        "ARerrp1": [1.90886819363],
        "ARerrp2": [0.249719455838],
        "Accelerationp1": [694.651550293],
        "Accelerationp2": [37.1348075867],
        "Centroidp1": [0.0762934833765],
        "Centroidp2": [0.121687211096],
        "Derivativep1": [766.163574219],
        "Derivativep2": [54.036857605],
        "Meanp1": [3.22341585159],
        "Meanp2": [0.982829928398],
        "Medianp1": [3.11821365356],
        "Medianp2": [8.01086425781e-05],
        "SpKurtp1": [0.00142550468445],
        "SpKurtp2": [3.35138225555],
        "SpSkewp1": [0.973341345787],
        "SpSkewp2": [1.88486969471],
        "SpSpreadp1": [0.0520468689501],
        "SpSpreadp2": [0.0438743010163],
        "pointdiffp1": [-3.14980077744],
        "pointdiffp2": [-4.35282611847],
        "pointmiddlep1": [-4.93135023117],
        "pointmiddlep2": [1.12693274021],
        "pointstartp1": [-5.89397287369],
        "pointstartp2": [4.97637939453],
        "slopeendp1": [-64.3541030884],
        "slopeendp2": [116.667304993],
        "slopeerrorp1": [1.17660284042],
        "slopeerrorp2": [0.28583368659],
        "slopemiddlep1": [-170.511276245],
        "slopemiddlep2": [-93.1619644165],
        "slopestartp1": [177.325180054],
        "slopestartp2": [-147.16859436],
        "stddevp1": [7.55307912827],
        "stddevp2": [1.85986077785]
    },
    "mfcc4": {
        "ARc0p1": [-1.17549435082e-38],
        "ARc0p2": [0.0279581751674],
        "ARc1p1": [-1.17549435082e-38],
        "ARc1p2": [-1.17549435082e-38],
        "ARc2p1": [0.373492836952],
        "ARc2p2": [0.655999302864],
        "ARc3p1": [-1.17549435082e-38],
        "ARc3p2": [-1.17549435082e-38],
        "ARc4p1": [0.990330278873],
        "ARc4p2": [1.69287276268],
        "ARerrp1": [1.6097496748],
        "ARerrp2": [0.202906429768],
        "Accelerationp1": [459.662353516],
        "Accelerationp2": [37.140335083],
        "Centroidp1": [0.487576752901],
        "Centroidp2": [0.267223834991],
        "Derivativep1": [480.056030273],
        "Derivativep2": [48.2756538391],
        "Meanp1": [-14.0039930344],
        "Meanp2": [0.258656829596],
        "Medianp1": [-12.9556083679],
        "Medianp2": [-6.103515625e-05],
        "SpKurtp1": [0.573937654495],
        "SpKurtp2": [2.33895206451],
        "SpSkewp1": [1.37107825279],
        "SpSkewp2": [1.56599104404],
        "SpSpreadp1": [0.0877378210425],
        "SpSpreadp2": [0.0458219945431],
        "pointdiffp1": [-5.93319892883],
        "pointdiffp2": [3.20447206497],
        "pointmiddlep1": [0.693665504456],
        "pointmiddlep2": [0.711993217468],
        "pointstartp1": [-10.3192300797],
        "pointstartp2": [-1.79592585564],
        "slopeendp1": [-166.139923096],
        "slopeendp2": [161.958099365],
        "slopeerrorp1": [0.536267876625],
        "slopeerrorp2": [0.440294295549],
        "slopemiddlep1": [143.140090942],
        "slopemiddlep2": [-128.502212524],
        "slopestartp1": [-168.319946289],
        "slopestartp2": [165.741027832],
        "stddevp1": [3.50014972687],
        "stddevp2": [1.18451535702]
    },
    "mfcc5": {
        "ARc0p1": [-1.17549435082e-38],
        "ARc0p2": [0.0147168952972],
        "ARc1p1": [-1.17549435082e-38],
        "ARc1p2": [0.0601849630475],
        "ARc2p1": [-1.17549435082e-38],
        "ARc2p2": [0.404493540525],
        "ARc3p1": [-1.17549435082e-38],
        "ARc3p2": [-1.17549435082e-38],
        "ARc4p1": [0.493152052164],
        "ARc4p2": [1.5005825758],
        "ARerrp1": [1.39209854603],
        "ARerrp2": [0.138552516699],
        "Accelerationp1": [735.345031738],
        "Accelerationp2": [27.5688285828],
        "Centroidp1": [0.506375432014],
        "Centroidp2": [-0.0634309202433],
        "Derivativep1": [608.358947754],
        "Derivativep2": [34.2743835449],
        "Meanp1": [-28.448348999],
        "Meanp2": [-0.343553304672],
        "Medianp1": [-28.4921684265],
        "Medianp2": [2.28881835938e-05],
        "SpKurtp1": [1.55876302719],
        "SpKurtp2": [0.908754110336],
        "SpSkewp1": [1.63881981373],
        "SpSkewp2": [1.35304653645],
        "SpSpreadp1": [0.0744061842561],
        "SpSpreadp2": [0.0659010633826],
        "pointdiffp1": [-3.01774740219],
        "pointdiffp2": [9.06295585632],
        "pointmiddlep1": [2.37526869774],
        "pointmiddlep2": [0.868323981762],
        "pointstartp1": [-23.402545929],
        "pointstartp2": [-7.09779548645],
        "slopeendp1": [153.895111084],
        "slopeendp2": [145.909210205],
        "slopeerrorp1": [1.10011851788],
        "slopeerrorp2": [0.165530517697],
        "slopemiddlep1": [10.7243032455],
        "slopemiddlep2": [-81.8785171509],
        "slopestartp1": [-169.311080933],
        "slopestartp2": [161.699584961],
        "stddevp1": [3.58262944221],
        "stddevp2": [1.17202234268]
    },
    "mfcc6": {
        "ARc0p1": [-1.17549435082e-38],
        "ARc0p2": [-1.17549435082e-38],
        "ARc1p1": [-1.17549435082e-38],
        "ARc1p2": [0.0179019551724],
        "ARc2p1": [-1.17549435082e-38],
        "ARc2p2": [0.423272132874],
        "ARc3p1": [-1.17549435082e-38],
        "ARc3p2": [-1.17549435082e-38],
        "ARc4p1": [0.110487356782],
        "ARc4p2": [1.34874379635],
        "ARerrp1": [0.954362392426],
        "ARerrp2": [0.121933311224],
        "Accelerationp1": [458.694458008],
        "Accelerationp2": [21.598482132],
        "Centroidp1": [0.474606662989],
        "Centroidp2": [0.0394037030637],
        "Derivativep1": [572.387634277],
        "Derivativep2": [26.781961441],
        "Meanp1": [-14.9381608963],
        "Meanp2": [-0.529733121395],
        "Medianp1": [-14.704750061],
        "Medianp2": [-2.67028808594e-05],
        "SpKurtp1": [-0.454815864563],
        "SpKurtp2": [0.325614929199],
        "SpSkewp1": [0.983582437038],
        "SpSkewp2": [1.17603302002],
        "SpSpreadp1": [0.102349735796],
        "SpSpreadp2": [0.0719175860286],
        "pointdiffp1": [8.36096763611],
        "pointdiffp2": [7.55446624756],
        "pointmiddlep1": [1.22155690193],
        "pointmiddlep2": [0.911679208279],
        "pointstartp1": [-22.8892173767],
        "pointstartp2": [-6.37784385681],
        "slopeendp1": [103.094467163],
        "slopeendp2": [135.280380249],
        "slopeerrorp1": [0.287463217974],
        "slopeerrorp2": [0.100647799671],
        "slopemiddlep1": [-59.6049880981],
        "slopemiddlep2": [-56.6363792419],
        "slopestartp1": [163.812896729],
        "slopestartp2": [160.182601929],
        "stddevp1": [3.25562334061],
        "stddevp2": [0.894927680492]
    },
    "mfcc7": {
        "ARc0p1": [0.115580752492],
        "ARc0p2": [-1.17549435082e-38],
        "ARc1p1": [0.0205839797854],
        "ARc1p2": [0.0800256729126],
        "ARc2p1": [0.689084112644],
        "ARc2p2": [0.22343043983],
        "ARc3p1": [-1.17549435082e-38],
        "ARc3p2": [-1.17549435082e-38],
        "ARc4p1": [0.912639379501],
        "ARc4p2": [1.29389548302],
        "ARerrp1": [1.34697699547],
        "ARerrp2": [0.158000484109],
        "Accelerationp1": [382.851074219],
        "Accelerationp2": [23.235710144],
        "Centroidp1": [0.470396876335],
        "Centroidp2": [0.0887324437499],
        "Derivativep1": [480.308624268],
        "Derivativep2": [31.4491481781],
        "Meanp1": [-23.209854126],
        "Meanp2": [-0.699083566666],
        "Medianp1": [-22.5084381104],
        "Medianp2": [-5.34057617188e-05],
        "SpKurtp1": [0.81165933609],
        "SpKurtp2": [-0.121778726578],
        "SpSkewp1": [1.48324048519],
        "SpSkewp2": [0.966668605804],
        "SpSpreadp1": [0.0878751501441],
        "SpSpreadp2": [0.074959769845],
        "pointdiffp1": [0.712713003159],
        "pointdiffp2": [5.8981051445],
        "pointmiddlep1": [-3.92275094986],
        "pointmiddlep2": [0.977056503296],
        "pointstartp1": [-21.5961112976],
        "pointstartp2": [-5.52171897888],
        "slopeendp1": [-176.977218628],
        "slopeendp2": [99.5083847046],
        "slopeerrorp1": [2.43287992477],
        "slopeerrorp2": [0.0812380686402],
        "slopemiddlep1": [176.090087891],
        "slopemiddlep2": [-5.13260555267],
        "slopestartp1": [-178.436935425],
        "slopestartp2": [157.371368408],
        "stddevp1": [3.0768661499],
        "stddevp2": [1.0692833662]
    },
    "mfcc8": {
        "ARc0p1": [-1.17549435082e-38],
        "ARc0p2": [-1.17549435082e-38],
        "ARc1p1": [-1.17549435082e-38],
        "ARc1p2": [-1.17549435082e-38],
        "ARc2p1": [0.598953604698],
        "ARc2p2": [0.861151278019],
        "ARc3p1": [-1.17549435082e-38],
        "ARc3p2": [-1.17549435082e-38],
        "ARc4p1": [0.640069961548],
        "ARc4p2": [1.55739557743],
        "ARerrp1": [0.945960879326],
        "ARerrp2": [0.181465238333],
        "Accelerationp1": [272.592681885],
        "Accelerationp2": [26.0583286285],
        "Centroidp1": [0.450174331665],
        "Centroidp2": [0.089447312057],
        "Derivativep1": [607.320617676],
        "Derivativep2": [38.756313324],
        "Meanp1": [-15.8619060516],
        "Meanp2": [-1.16261553764],
        "Medianp1": [-14.8969116211],
        "Medianp2": [-4.57763671875e-05],
        "SpKurtp1": [0.607323408127],
        "SpKurtp2": [0.873065710068],
        "SpSkewp1": [1.32887899876],
        "SpSkewp2": [1.36224210262],
        "SpSpreadp1": [0.0774063840508],
        "SpSpreadp2": [0.0636580809951],
        "pointdiffp1": [9.01347255707],
        "pointdiffp2": [9.71336364746],
        "pointmiddlep1": [1.25048351288],
        "pointmiddlep2": [0.978585958481],
        "pointstartp1": [-24.5964298248],
        "pointstartp2": [-9.11472225189],
        "slopeendp1": [-116.230010986],
        "slopeendp2": [98.0635147095],
        "slopeerrorp1": [0.277204990387],
        "slopeerrorp2": [0.0725591257215],
        "slopemiddlep1": [77.5137557983],
        "slopemiddlep2": [-3.77977156639],
        "slopestartp1": [154.371688843],
        "slopestartp2": [157.293777466],
        "stddevp1": [3.5643184185],
        "stddevp2": [1.7642800808]
    },
    "mfcc9": {
        "ARc0p1": [-1.17549435082e-38],
        "ARc0p2": [-1.17549435082e-38],
        "ARc1p1": [-1.17549435082e-38],
        "ARc1p2": [-1.17549435082e-38],
        "ARc2p1": [0.79442024231],
        "ARc2p2": [0.746911168098],
        "ARc3p1": [-1.17549435082e-38],
        "ARc3p2": [-1.17549435082e-38],
        "ARc4p1": [1.11815273762],
        "ARc4p2": [1.50492107868],
        "ARerrp1": [1.08447360992],
        "ARerrp2": [0.224239826202],
        "Accelerationp1": [390.356781006],
        "Accelerationp2": [33.94165802],
        "Centroidp1": [0.397601664066],
        "Centroidp2": [0.0801191702485],
        "Derivativep1": [645.009643555],
        "Derivativep2": [47.9405555725],
        "Meanp1": [-15.081199646],
        "Meanp2": [-1.78089249134],
        "Medianp1": [-12.526550293],
        "Medianp2": [-2.28881835938e-05],
        "SpKurtp1": [1.8758764267],
        "SpKurtp2": [1.63792848587],
        "SpSkewp1": [1.62135887146],
        "SpSkewp2": [1.57288300991],
        "SpSpreadp1": [0.0509601458907],
        "SpSpreadp2": [0.0553264990449],
        "pointdiffp1": [2.26087760925],
        "pointdiffp2": [16.796880722],
        "pointmiddlep1": [0.230671659112],
        "pointmiddlep2": [0.960647046566],
        "pointstartp1": [-15.8310642242],
        "pointstartp2": [-15.3315086365],
        "slopeendp1": [-176.839187622],
        "slopeendp2": [112.655578613],
        "slopeerrorp1": [1.30465900898],
        "slopeerrorp2": [0.0590174384415],
        "slopemiddlep1": [174.320373535],
        "slopemiddlep2": [-19.4959259033],
        "slopestartp1": [-177.016540527],
        "slopestartp2": [158.172943115],
        "stddevp1": [6.3621931076],
        "stddevp2": [2.70783734322]
    },
    "pitchSalience": {
        "ARc0p1": [0.256666749716],
        "ARc0p2": [0.023384610191],
        "ARc1p1": [-1.17549435082e-38],
        "ARc1p2": [-1.17549435082e-38],
        "ARc2p1": [0.795816242695],
        "ARc2p2": [0.221044421196],
        "ARc3p1": [-1.17549435082e-38],
        "ARc3p2": [-1.17549435082e-38],
        "ARc4p1": [1.29803395271],
        "ARc4p2": [1.1910046339],
        "ARerrp1": [0.0228398963809],
        "ARerrp2": [0.0425185710192],
        "Accelerationp1": [7.27911615372],
        "Accelerationp2": [6.17043447495],
        "Centroidp1": [0.481550782919],
        "Centroidp2": [0.571073174477],
        "Derivativep1": [10.7773923874],
        "Derivativep2": [7.74893522263],
        "Meanp1": [0.501766681671],
        "Meanp2": [0.498449504375],
        "Medianp1": [0.497039109468],
        "Medianp2": [0.52970957756],
        "SpKurtp1": [0.0988447666168],
        "SpKurtp2": [1.89267921448],
        "SpSkewp1": [1.19282865524],
        "SpSkewp2": [1.64407742023],
        "SpSpreadp1": [0.0975118726492],
        "SpSpreadp2": [0.0561148151755],
        "pointdiffp1": [-0.373536229134],
        "pointdiffp2": [0.128128662705],
        "pointmiddlep1": [1.25604605675],
        "pointmiddlep2": [0.364976704121],
        "pointstartp1": [0.865041553974],
        "pointstartp2": [0.445904582739],
        "slopeendp1": [-135.753265381],
        "slopeendp2": [-168.637512207],
        "slopeerrorp1": [0.122042857111],
        "slopeerrorp2": [0.749071955681],
        "slopemiddlep1": [102.321159363],
        "slopemiddlep2": [163.258544922],
        "slopestartp1": [-166.59375],
        "slopestartp2": [-169.733963013],
        "stddevp1": [0.10167568922],
        "stddevp2": [0.153499677777]
    },
    "pitchYin-st": {
        "ARc0p1": [201.354400635],
        "ARc0p2": [115.712471008],
        "ARc1p1": [-1.17549435082e-38],
        "ARc1p2": [0.0263658873737],
        "ARc2p1": [0.356025248766],
        "ARc2p2": [0.113828845322],
        "ARc3p1": [-1.17549435082e-38],
        "ARc3p2": [-1.17549435082e-38],
        "ARc4p1": [0.779031872749],
        "ARc4p2": [0.83028537035],
        "ARerrp1": [6.31782913208],
        "ARerrp2": [170.066467285],
        "Accelerationp1": [58.2665405273],
        "Accelerationp2": [83.4826507568],
        "Centroidp1": [-49.1370201111],
        "Centroidp2": [-45.7313079834],
        "Derivativep1": [54.1878852844],
        "Derivativep2": [77.8268661499],
        "Meanp1": [25.8585395813],
        "Meanp2": [54.3295249939],
        "Medianp1": [25.6053981781],
        "Medianp2": [58.5895309448],
        "SpKurtp1": [-0.0772342681885],
        "SpKurtp2": [0.423971891403],
        "SpSkewp1": [1.19115102291],
        "SpSkewp2": [1.26730108261],
        "SpSpreadp1": [0.104511223733],
        "SpSpreadp2": [0.0753407031298],
        "pointdiffp1": [-138.360076904],
        "pointdiffp2": [2375.56665039],
        "pointmiddlep1": [0.765605211258],
        "pointmiddlep2": [1.57738685608],
        "pointstartp1": [334.806274414],
        "pointstartp2": [-289.502593994],
        "slopeendp1": [-135.658157349],
        "slopeendp2": [-162.093597412],
        "slopeerrorp1": [0.10125092417],
        "slopeerrorp2": [0.284745156765],
        "slopemiddlep1": [28.9538154602],
        "slopemiddlep2": [136.692337036],
        "slopestartp1": [-155.360931396],
        "slopestartp2": [132.488540649],
        "stddevp1": [24.5063762665],
        "stddevp2": [54.0845451355]
    },
    "pitchYinConfidence": {
        "ARc0p1": [0.120967403054],
        "ARc0p2": [0.0293111819774],
        "ARc1p1": [0.159442469478],
        "ARc1p2": [-1.17549435082e-38],
        "ARc2p1": [-1.17549435082e-38],
        "ARc2p2": [0.411257326603],
        "ARc3p1": [-1.17549435082e-38],
        "ARc3p2": [-1.17549435082e-38],
        "ARc4p1": [1.03195786476],
        "ARc4p2": [1.27789986134],
        "ARerrp1": [0.0262489616871],
        "ARerrp2": [0.0283551365137],
        "Accelerationp1": [9.55257034302],
        "Accelerationp2": [4.63916826248],
        "Centroidp1": [0.478540271521],
        "Centroidp2": [0.499211847782],
        "Derivativep1": [10.1946191788],
        "Derivativep2": [5.43360853195],
        "Meanp1": [0.457630395889],
        "Meanp2": [0.72281473875],
        "Medianp1": [0.439095795155],
        "Medianp2": [0.761337578297],
        "SpKurtp1": [1.33282756805],
        "SpKurtp2": [3.29229402542],
        "SpSkewp1": [1.67921638489],
        "SpSkewp2": [1.98589837551],
        "SpSpreadp1": [0.0898951664567],
        "SpSpreadp2": [0.0461040884256],
        "pointdiffp1": [-0.0184409525245],
        "pointdiffp2": [-0.194565579295],
        "pointmiddlep1": [-8.37966537476],
        "pointmiddlep2": [-0.763008117676],
        "pointstartp1": [0.364507496357],
        "pointstartp2": [0.65646725893],
        "slopeendp1": [-165.733261108],
        "slopeendp2": [-169.51121521],
        "slopeerrorp1": [2.93330860138],
        "slopeerrorp2": [0.408814877272],
        "slopemiddlep1": [-172.504226685],
        "slopemiddlep2": [109.727729797],
        "slopestartp1": [178.183319092],
        "slopestartp2": [-76.606842041],
        "stddevp1": [0.0774258598685],
        "stddevp2": [0.0854480713606]
    },
    "spectral_crest": {
        "ARc0p1": [3.28112959862],
        "ARc0p2": [0.850078344345],
        "ARc1p1": [-1.17549435082e-38],
        "ARc1p2": [-1.17549435082e-38],
        "ARc2p1": [1.2997174263],
        "ARc2p2": [0.593380868435],
        "ARc3p1": [-1.17549435082e-38],
        "ARc3p2": [-1.17549435082e-38],
        "ARc4p1": [1.86365246773],
        "ARc4p2": [1.8022351265],
        "ARerrp1": [0.46234613657],
        "ARerrp2": [0.60683709383],
        "Accelerationp1": [147.54145813],
        "Accelerationp2": [102.179740906],
        "Centroidp1": [0.464611500502],
        "Centroidp2": [0.506450772285],
        "Derivativep1": [244.515762329],
        "Derivativep2": [149.174621582],
        "Meanp1": [17.4202728271],
        "Meanp2": [20.831079483],
        "Medianp1": [17.6378860474],
        "Medianp2": [22.7506008148],
        "SpKurtp1": [1.54856395721],
        "SpKurtp2": [6.40649032593],
        "SpSkewp1": [1.69415640831],
        "SpSkewp2": [2.48362326622],
        "SpSpreadp1": [0.0822881609201],
        "SpSpreadp2": [0.034163992852],
        "pointdiffp1": [-0.380497038364],
        "pointdiffp2": [-11.0341882706],
        "pointmiddlep1": [-12.6458683014],
        "pointmiddlep2": [-0.192882806063],
        "pointstartp1": [14.484292984],
        "pointstartp2": [21.2572975159],
        "slopeendp1": [177.491409302],
        "slopeendp2": [-168.008987427],
        "slopeerrorp1": [1.93489038944],
        "slopeerrorp2": [0.238241180778],
        "slopemiddlep1": [-177.737304688],
        "slopemiddlep2": [123.848800659],
        "slopestartp1": [179.240966797],
        "slopestartp2": [-151.778640747],
        "stddevp1": [2.74130177498],
        "stddevp2": [3.7911939621]
    },
    "spectral_flatness_db": {
        "ARc0p1": [0.0121059818193],
        "ARc0p2": [0.00848001986742],
        "ARc1p1": [-1.17549435082e-38],
        "ARc1p2": [-1.17549435082e-38],
        "ARc2p1": [1.39330625534],
        "ARc2p2": [1.10647368431],
        "ARc3p1": [-1.17549435082e-38],
        "ARc3p2": [-1.17549435082e-38],
        "ARc4p1": [2.25026345253],
        "ARc4p2": [2.13270926476],
        "ARerrp1": [0.00320342392661],
        "ARerrp2": [0.00606565922499],
        "Accelerationp1": [1.31325626373],
        "Accelerationp2": [1.15487825871],
        "Centroidp1": [0.452584534883],
        "Centroidp2": [0.463758021593],
        "Derivativep1": [2.46706461906],
        "Derivativep2": [1.77666246891],
        "Meanp1": [0.203636556864],
        "Meanp2": [0.222830206156],
        "Medianp1": [0.193612396717],
        "Medianp2": [0.229815378785],
        "SpKurtp1": [1.50166702271],
        "SpKurtp2": [6.70123195648],
        "SpSkewp1": [1.68083155155],
        "SpSkewp2": [2.41737771034],
        "SpSpreadp1": [0.0830214247108],
        "SpSpreadp2": [0.0285241808742],
        "pointdiffp1": [-0.059461530298],
        "pointdiffp2": [-0.129415974021],
        "pointmiddlep1": [-0.0685898214579],
        "pointmiddlep2": [-0.0187658090144],
        "pointstartp1": [0.212236568332],
        "pointstartp2": [0.242833718657],
        "slopeendp1": [99.8160400391],
        "slopeendp2": [-154.075134277],
        "slopeerrorp1": [0.240372732282],
        "slopeerrorp2": [0.218063339591],
        "slopemiddlep1": [-145.606948853],
        "slopemiddlep2": [-40.139705658],
        "slopestartp1": [160.223800659],
        "slopestartp2": [-21.9842205048],
        "stddevp1": [0.032190002501],
        "stddevp2": [0.0364483520389]
    },
    "tristimulus0": {
        "ARc0p1": [0.0574405603111],
        "ARc0p2": [0.0314820893109],
        "ARc1p1": [0.328239291906],
        "ARc1p2": [0.0462928414345],
        "ARc2p1": [0.23824468255],
        "ARc2p2": [0.165652364492],
        "ARc3p1": [-1.17549435082e-38],
        "ARc3p2": [0.186455890536],
        "ARc4p1": [-1.17549435082e-38],
        "ARc4p2": [0.237140133977],
        "ARerrp1": [0.0730353817344],
        "ARerrp2": [0.0962317809463],
        "Accelerationp1": [23.240480423],
        "Accelerationp2": [15.5163326263],
        "Centroidp1": [0.383683562279],
        "Centroidp2": [0.363535434008],
        "Derivativep1": [26.2219982147],
        "Derivativep2": [16.9212055206],
        "Meanp1": [0.16529366374],
        "Meanp2": [0.0867064297199],
        "Medianp1": [0.170235216618],
        "Medianp2": [0.0135840438306],
        "SpKurtp1": [-1.09088754654],
        "SpKurtp2": [-1.30017948151],
        "SpSkewp1": [0.557240068913],
        "SpSkewp2": [0.248807758093],
        "SpSpreadp1": [0.105440609157],
        "SpSpreadp2": [0.0990419834852],
        "pointdiffp1": [-0.00965438038111],
        "pointdiffp2": [0.0198215730488],
        "pointmiddlep1": [-2.41078615189],
        "pointmiddlep2": [-7.05551671982],
        "pointstartp1": [0.152557209134],
        "pointstartp2": [0.176518440247],
        "slopeendp1": [178.965957642],
        "slopeendp2": [178.411468506],
        "slopeerrorp1": [10.6568403244],
        "slopeerrorp2": [5.11732435226],
        "slopemiddlep1": [-178.172988892],
        "slopemiddlep2": [-174.110870361],
        "slopestartp1": [179.145736694],
        "slopestartp2": [170.192993164],
        "stddevp1": [0.131438568234],
        "stddevp2": [0.108805336058]
    },
    "tristimulus1": {
        "ARc0p1": [0.222331345081],
        "ARc0p2": [0.0597303546965],
        "ARc1p1": [0.225143402815],
        "ARc1p2": [0.141316384077],
        "ARc2p1": [-1.17549435082e-38],
        "ARc2p2": [0.235520645976],
        "ARc3p1": [-1.17549435082e-38],
        "ARc3p2": [0.221402749419],
        "ARc4p1": [-1.17549435082e-38],
        "ARc4p2": [0.165207028389],
        "ARerrp1": [0.0714905709028],
        "ARerrp2": [0.0933456495404],
        "Accelerationp1": [23.2385139465],
        "Accelerationp2": [14.7787952423],
        "Centroidp1": [0.427841931581],
        "Centroidp2": [0.383426070213],
        "Derivativep1": [23.0099563599],
        "Derivativep2": [16.8000564575],
        "Meanp1": [0.218837857246],
        "Meanp2": [0.253688156605],
        "Medianp1": [0.194538533688],
        "Medianp2": [0.20459574461],
        "SpKurtp1": [-1.15701544285],
        "SpKurtp2": [-1.34419631958],
        "SpSkewp1": [0.553427994251],
        "SpSkewp2": [0.240120992064],
        "SpSpreadp1": [0.118479430676],
        "SpSpreadp2": [0.108154021204],
        "pointdiffp1": [-0.348842948675],
        "pointdiffp2": [-0.25283703208],
        "pointmiddlep1": [0.83787560463],
        "pointmiddlep2": [0.241714939475],
        "pointstartp1": [0.4669252038],
        "pointstartp2": [0.336622267962],
        "slopeendp1": [-140.701812744],
        "slopeendp2": [-2.82566761971],
        "slopeerrorp1": [0.258736491203],
        "slopeerrorp2": [0.370888471603],
        "slopemiddlep1": [59.8923683167],
        "slopemiddlep2": [-126.967376709],
        "slopestartp1": [-159.40447998],
        "slopestartp2": [127.808563232],
        "stddevp1": [0.109641045332],
        "stddevp2": [0.136956140399]
    },
    "tristimulus2": {
        "ARc0p1": [0.289094775915],
        "ARc0p2": [0.0150208314881],
        "ARc1p1": [0.0714870467782],
        "ARc1p2": [0.019278222695],
        "ARc2p1": [0.291647285223],
        "ARc2p2": [-1.17549435082e-38],
        "ARc3p1": [0.210355252028],
        "ARc3p2": [0.0642038285732],
        "ARc4p1": [0.0569268427789],
        "ARc4p2": [0.933008313179],
        "ARerrp1": [0.0189196337014],
        "ARerrp2": [0.0288825631142],
        "Accelerationp1": [5.85797691345],
        "Accelerationp2": [4.20749807358],
        "Centroidp1": [0.556858420372],
        "Centroidp2": [0.552348911762],
        "Derivativep1": [6.85875701904],
        "Derivativep2": [4.92668390274],
        "Meanp1": [0.615868389606],
        "Meanp2": [0.643990039825],
        "Medianp1": [0.675192415714],
        "Medianp2": [0.705328881741],
        "SpKurtp1": [0.95735001564],
        "SpKurtp2": [2.67312526703],
        "SpSkewp1": [1.51519703865],
        "SpSkewp2": [1.90829944611],
        "SpSpreadp1": [0.0850862041116],
        "SpSpreadp2": [0.0585303232074],
        "pointdiffp1": [0.358496963978],
        "pointdiffp2": [-0.0561224296689],
        "pointmiddlep1": [0.750389695168],
        "pointmiddlep2": [-2.98912072182],
        "pointstartp1": [0.38051751256],
        "pointstartp2": [0.541661262512],
        "slopeendp1": [-28.8205566406],
        "slopeendp2": [-177.956802368],
        "slopeerrorp1": [0.0745836645365],
        "slopeerrorp2": [1.60941910744],
        "slopemiddlep1": [96.8693618774],
        "slopemiddlep2": [174.144714355],
        "slopestartp1": [120.402565002],
        "slopestartp2": [-175.931091309],
        "stddevp1": [0.107510998845],
        "stddevp2": [0.168006211519]
    }
},
"slice": {
    "time": [[0, 4.98999977112]]
},
"Class": {
    "type0": "Snare",
    "type1": "NoTimbre",
    "type2": "rSensiNoSn",
    "type3": "none",
    "type4": "none"
},
"audiopath": "\/Users\/mhermant\/Documents\/Work\/Datasets\/DrumKitFromHell\/Snare.NoTimbre.rSensiNoSn R05  x.wav"
}